[
  {
    "url": "https://api.github.com/gists/7f86bd9f16fd9d8f5e22458d632969c7",
    "forks_url": "https://api.github.com/gists/7f86bd9f16fd9d8f5e22458d632969c7/forks",
    "commits_url": "https://api.github.com/gists/7f86bd9f16fd9d8f5e22458d632969c7/commits",
    "id": "7f86bd9f16fd9d8f5e22458d632969c7",
    "node_id": "G_kwDOArwYiNoAIDdmODZiZDlmMTZmZDlkOGY1ZTIyNDU4ZDYzMjk2OWM3",
    "git_pull_url": "https://gist.github.com/7f86bd9f16fd9d8f5e22458d632969c7.git",
    "git_push_url": "https://gist.github.com/7f86bd9f16fd9d8f5e22458d632969c7.git",
    "html_url": "https://gist.github.com/vossisboss/7f86bd9f16fd9d8f5e22458d632969c7",
    "files": {
      "gistfile1.txt": {
        "filename": "gistfile1.txt",
        "type": "text/plain",
        "language": "Text",
        "raw_url": "https://gist.githubusercontent.com/vossisboss/7f86bd9f16fd9d8f5e22458d632969c7/raw/52ab5746f4f037496e18f439fb4b2a2fe6786106/gistfile1.txt",
        "size": 2805
      }
    },
    "public": true,
    "created_at": "2025-11-20T21:20:18Z",
    "updated_at": "2025-11-20T21:20:19Z",
    "description": "Collecting maintainer user names from PyPI using a txt file of URLs",
    "comments": 0,
    "user": null,
    "comments_enabled": true,
    "comments_url": "https://api.github.com/gists/7f86bd9f16fd9d8f5e22458d632969c7/comments",
    "owner": {
      "login": "vossisboss",
      "id": 45881480,
      "node_id": "MDQ6VXNlcjQ1ODgxNDgw",
      "avatar_url": "https://avatars.githubusercontent.com/u/45881480?v=4",
      "gravatar_id": "",
      "url": "https://api.github.com/users/vossisboss",
      "html_url": "https://github.com/vossisboss",
      "followers_url": "https://api.github.com/users/vossisboss/followers",
      "following_url": "https://api.github.com/users/vossisboss/following{/other_user}",
      "gists_url": "https://api.github.com/users/vossisboss/gists{/gist_id}",
      "starred_url": "https://api.github.com/users/vossisboss/starred{/owner}{/repo}",
      "subscriptions_url": "https://api.github.com/users/vossisboss/subscriptions",
      "organizations_url": "https://api.github.com/users/vossisboss/orgs",
      "repos_url": "https://api.github.com/users/vossisboss/repos",
      "events_url": "https://api.github.com/users/vossisboss/events{/privacy}",
      "received_events_url": "https://api.github.com/users/vossisboss/received_events",
      "type": "User",
      "user_view_type": "public",
      "site_admin": false
    },
    "truncated": false
  },
  {
    "url": "https://api.github.com/gists/06955e2ff855da3c65a7fe9c8e4be02c",
    "forks_url": "https://api.github.com/gists/06955e2ff855da3c65a7fe9c8e4be02c/forks",
    "commits_url": "https://api.github.com/gists/06955e2ff855da3c65a7fe9c8e4be02c/commits",
    "id": "06955e2ff855da3c65a7fe9c8e4be02c",
    "node_id": "G_kwDNyCHaACAwNjk1NWUyZmY4NTVkYTNjNjVhN2ZlOWM4ZTRiZTAyYw",
    "git_pull_url": "https://gist.github.com/06955e2ff855da3c65a7fe9c8e4be02c.git",
    "git_push_url": "https://gist.github.com/06955e2ff855da3c65a7fe9c8e4be02c.git",
    "html_url": "https://gist.github.com/skylar/06955e2ff855da3c65a7fe9c8e4be02c",
    "files": {
      "gistfile1.txt": {
        "filename": "gistfile1.txt",
        "type": "text/plain",
        "language": "Text",
        "raw_url": "https://gist.githubusercontent.com/skylar/06955e2ff855da3c65a7fe9c8e4be02c/raw/d488452472a61dba7dae235e4fd317c05b6bc2c4/gistfile1.txt",
        "size": 562
      }
    },
    "public": true,
    "created_at": "2025-11-20T21:20:08Z",
    "updated_at": "2025-11-20T21:20:24Z",
    "description": "",
    "comments": 0,
    "user": null,
    "comments_enabled": true,
    "comments_url": "https://api.github.com/gists/06955e2ff855da3c65a7fe9c8e4be02c/comments",
    "owner": {
      "login": "skylar",
      "id": 51233,
      "node_id": "MDQ6VXNlcjUxMjMz",
      "avatar_url": "https://avatars.githubusercontent.com/u/51233?v=4",
      "gravatar_id": "",
      "url": "https://api.github.com/users/skylar",
      "html_url": "https://github.com/skylar",
      "followers_url": "https://api.github.com/users/skylar/followers",
      "following_url": "https://api.github.com/users/skylar/following{/other_user}",
      "gists_url": "https://api.github.com/users/skylar/gists{/gist_id}",
      "starred_url": "https://api.github.com/users/skylar/starred{/owner}{/repo}",
      "subscriptions_url": "https://api.github.com/users/skylar/subscriptions",
      "organizations_url": "https://api.github.com/users/skylar/orgs",
      "repos_url": "https://api.github.com/users/skylar/repos",
      "events_url": "https://api.github.com/users/skylar/events{/privacy}",
      "received_events_url": "https://api.github.com/users/skylar/received_events",
      "type": "User",
      "user_view_type": "public",
      "site_admin": false
    },
    "truncated": false
  },
  {
    "url": "https://api.github.com/gists/d42a249ede0cbb2d4e56a20c7fb20796",
    "forks_url": "https://api.github.com/gists/d42a249ede0cbb2d4e56a20c7fb20796/forks",
    "commits_url": "https://api.github.com/gists/d42a249ede0cbb2d4e56a20c7fb20796/commits",
    "id": "d42a249ede0cbb2d4e56a20c7fb20796",
    "node_id": "G_kwDOAF-wA9oAIGQ0MmEyNDllZGUwY2JiMmQ0ZTU2YTIwYzdmYjIwNzk2",
    "git_pull_url": "https://gist.github.com/d42a249ede0cbb2d4e56a20c7fb20796.git",
    "git_push_url": "https://gist.github.com/d42a249ede0cbb2d4e56a20c7fb20796.git",
    "html_url": "https://gist.github.com/choco-bot/d42a249ede0cbb2d4e56a20c7fb20796",
    "files": {
      "FilesSnapshot.xml": {
        "filename": "FilesSnapshot.xml",
        "type": "application/xml",
        "language": "XML",
        "raw_url": "https://gist.githubusercontent.com/choco-bot/d42a249ede0cbb2d4e56a20c7fb20796/raw/765ec75ba846edce23706ab0db2db054e6b4ef40/FilesSnapshot.xml",
        "size": 1071
      },
      "Install.txt": {
        "filename": "Install.txt",
        "type": "text/plain",
        "language": "Text",
        "raw_url": "https://gist.githubusercontent.com/choco-bot/d42a249ede0cbb2d4e56a20c7fb20796/raw/7fcf2a75701e139f0a2e1f01797f34c827ba6ff5/Install.txt",
        "size": 178085
      },
      "Uninstall.txt": {
        "filename": "Uninstall.txt",
        "type": "text/plain",
        "language": "Text",
        "raw_url": "https://gist.githubusercontent.com/choco-bot/d42a249ede0cbb2d4e56a20c7fb20796/raw/a1e6eb3e317df43b50fb69eebf4fa155992cb9a9/Uninstall.txt",
        "size": 54129
      },
      "_Summary.md": {
        "filename": "_Summary.md",
        "type": "text/markdown",
        "language": "Markdown",
        "raw_url": "https://gist.githubusercontent.com/choco-bot/d42a249ede0cbb2d4e56a20c7fb20796/raw/9fcd58158d30189d6aa421804fcaf47b77cb2bf8/_Summary.md",
        "size": 496
      }
    },
    "public": true,
    "created_at": "2025-11-20T21:20:01Z",
    "updated_at": "2025-11-20T21:20:02Z",
    "description": "rpcs3 v0.0.38-alpha18367 - Passed - Package Tests Results",
    "comments": 0,
    "user": null,
    "comments_enabled": true,
    "comments_url": "https://api.github.com/gists/d42a249ede0cbb2d4e56a20c7fb20796/comments",
    "owner": {
      "login": "choco-bot",
      "id": 6270979,
      "node_id": "MDQ6VXNlcjYyNzA5Nzk=",
      "avatar_url": "https://avatars.githubusercontent.com/u/6270979?v=4",
      "gravatar_id": "",
      "url": "https://api.github.com/users/choco-bot",
      "html_url": "https://github.com/choco-bot",
      "followers_url": "https://api.github.com/users/choco-bot/followers",
      "following_url": "https://api.github.com/users/choco-bot/following{/other_user}",
      "gists_url": "https://api.github.com/users/choco-bot/gists{/gist_id}",
      "starred_url": "https://api.github.com/users/choco-bot/starred{/owner}{/repo}",
      "subscriptions_url": "https://api.github.com/users/choco-bot/subscriptions",
      "organizations_url": "https://api.github.com/users/choco-bot/orgs",
      "repos_url": "https://api.github.com/users/choco-bot/repos",
      "events_url": "https://api.github.com/users/choco-bot/events{/privacy}",
      "received_events_url": "https://api.github.com/users/choco-bot/received_events",
      "type": "User",
      "user_view_type": "public",
      "site_admin": false
    },
    "truncated": false
  },
  {
    "url": "https://api.github.com/gists/4b8494753a856990e6458d568eec8a27",
    "forks_url": "https://api.github.com/gists/4b8494753a856990e6458d568eec8a27/forks",
    "commits_url": "https://api.github.com/gists/4b8494753a856990e6458d568eec8a27/commits",
    "id": "4b8494753a856990e6458d568eec8a27",
    "node_id": "G_kwDODCd0utoAIDRiODQ5NDc1M2E4NTY5OTBlNjQ1OGQ1NjhlZWM4YTI3",
    "git_pull_url": "https://gist.github.com/4b8494753a856990e6458d568eec8a27.git",
    "git_push_url": "https://gist.github.com/4b8494753a856990e6458d568eec8a27.git",
    "html_url": "https://gist.github.com/amaweb-unifesp/4b8494753a856990e6458d568eec8a27",
    "files": {
      "sem-bloqueio-teclado-1.html": {
        "filename": "sem-bloqueio-teclado-1.html",
        "type": "text/html",
        "language": "HTML",
        "raw_url": "https://gist.githubusercontent.com/amaweb-unifesp/4b8494753a856990e6458d568eec8a27/raw/c07a77baaa40d94be41f8dc40cdc47e088a7535f/sem-bloqueio-teclado-1.html",
        "size": 3417
      }
    },
    "public": true,
    "created_at": "2025-11-20T21:18:57Z",
    "updated_at": "2025-11-20T21:18:57Z",
    "description": "sem-bloqueio-teclado-1",
    "comments": 0,
    "user": null,
    "comments_enabled": true,
    "comments_url": "https://api.github.com/gists/4b8494753a856990e6458d568eec8a27/comments",
    "owner": {
      "login": "amaweb-unifesp",
      "id": 203912378,
      "node_id": "U_kgDODCd0ug",
      "avatar_url": "https://avatars.githubusercontent.com/u/203912378?v=4",
      "gravatar_id": "",
      "url": "https://api.github.com/users/amaweb-unifesp",
      "html_url": "https://github.com/amaweb-unifesp",
      "followers_url": "https://api.github.com/users/amaweb-unifesp/followers",
      "following_url": "https://api.github.com/users/amaweb-unifesp/following{/other_user}",
      "gists_url": "https://api.github.com/users/amaweb-unifesp/gists{/gist_id}",
      "starred_url": "https://api.github.com/users/amaweb-unifesp/starred{/owner}{/repo}",
      "subscriptions_url": "https://api.github.com/users/amaweb-unifesp/subscriptions",
      "organizations_url": "https://api.github.com/users/amaweb-unifesp/orgs",
      "repos_url": "https://api.github.com/users/amaweb-unifesp/repos",
      "events_url": "https://api.github.com/users/amaweb-unifesp/events{/privacy}",
      "received_events_url": "https://api.github.com/users/amaweb-unifesp/received_events",
      "type": "User",
      "user_view_type": "public",
      "site_admin": false
    },
    "truncated": false
  },
  {
    "url": "https://api.github.com/gists/e23502569de32f57bd7081e4f43f23bb",
    "forks_url": "https://api.github.com/gists/e23502569de32f57bd7081e4f43f23bb/forks",
    "commits_url": "https://api.github.com/gists/e23502569de32f57bd7081e4f43f23bb/commits",
    "id": "e23502569de32f57bd7081e4f43f23bb",
    "node_id": "G_kwDODV6HntoAIGUyMzUwMjU2OWRlMzJmNTdiZDcwODFlNGY0M2YyM2Ji",
    "git_pull_url": "https://gist.github.com/e23502569de32f57bd7081e4f43f23bb.git",
    "git_push_url": "https://gist.github.com/e23502569de32f57bd7081e4f43f23bb.git",
    "html_url": "https://gist.github.com/charlescoleman-design/e23502569de32f57bd7081e4f43f23bb",
    "files": {
      "tritonai-quickbooks-eula.md": {
        "filename": "tritonai-quickbooks-eula.md",
        "type": "text/markdown",
        "language": "Markdown",
        "raw_url": "https://gist.githubusercontent.com/charlescoleman-design/e23502569de32f57bd7081e4f43f23bb/raw/0b3c581e0782f5352da7e7f2c9be0438c1664f59/tritonai-quickbooks-eula.md",
        "size": 1804
      }
    },
    "public": true,
    "created_at": "2025-11-20T21:18:30Z",
    "updated_at": "2025-11-20T21:18:30Z",
    "description": "TritonAI QuickBooks Integration - End-User License Agreement (Internal Use)",
    "comments": 0,
    "user": null,
    "comments_enabled": true,
    "comments_url": "https://api.github.com/gists/e23502569de32f57bd7081e4f43f23bb/comments",
    "owner": {
      "login": "charlescoleman-design",
      "id": 224298910,
      "node_id": "U_kgDODV6Hng",
      "avatar_url": "https://avatars.githubusercontent.com/u/224298910?v=4",
      "gravatar_id": "",
      "url": "https://api.github.com/users/charlescoleman-design",
      "html_url": "https://github.com/charlescoleman-design",
      "followers_url": "https://api.github.com/users/charlescoleman-design/followers",
      "following_url": "https://api.github.com/users/charlescoleman-design/following{/other_user}",
      "gists_url": "https://api.github.com/users/charlescoleman-design/gists{/gist_id}",
      "starred_url": "https://api.github.com/users/charlescoleman-design/starred{/owner}{/repo}",
      "subscriptions_url": "https://api.github.com/users/charlescoleman-design/subscriptions",
      "organizations_url": "https://api.github.com/users/charlescoleman-design/orgs",
      "repos_url": "https://api.github.com/users/charlescoleman-design/repos",
      "events_url": "https://api.github.com/users/charlescoleman-design/events{/privacy}",
      "received_events_url": "https://api.github.com/users/charlescoleman-design/received_events",
      "type": "User",
      "user_view_type": "public",
      "site_admin": false
    },
    "truncated": false
  },
  {
    "url": "https://api.github.com/gists/5051ad04f5de65354318f514e594ac2b",
    "forks_url": "https://api.github.com/gists/5051ad04f5de65354318f514e594ac2b/forks",
    "commits_url": "https://api.github.com/gists/5051ad04f5de65354318f514e594ac2b/commits",
    "id": "5051ad04f5de65354318f514e594ac2b",
    "node_id": "G_kwDOAePzx9oAIDUwNTFhZDA0ZjVkZTY1MzU0MzE4ZjUxNGU1OTRhYzJi",
    "git_pull_url": "https://gist.github.com/5051ad04f5de65354318f514e594ac2b.git",
    "git_push_url": "https://gist.github.com/5051ad04f5de65354318f514e594ac2b.git",
    "html_url": "https://gist.github.com/ferrata/5051ad04f5de65354318f514e594ac2b",
    "files": {
      "openapi.yaml": {
        "filename": "openapi.yaml",
        "type": "text/x-yaml",
        "language": "OASv3-yaml",
        "raw_url": "https://gist.githubusercontent.com/ferrata/5051ad04f5de65354318f514e594ac2b/raw/f546b4a8fb932074054b221f797e0736201bc315/openapi.yaml",
        "size": 68187
      }
    },
    "public": true,
    "created_at": "2025-11-20T21:17:54Z",
    "updated_at": "2025-11-20T21:17:54Z",
    "description": "OpenAPI spec for PR #2082",
    "comments": 0,
    "user": null,
    "comments_enabled": true,
    "comments_url": "https://api.github.com/gists/5051ad04f5de65354318f514e594ac2b/comments",
    "owner": {
      "login": "ferrata",
      "id": 31716295,
      "node_id": "MDQ6VXNlcjMxNzE2Mjk1",
      "avatar_url": "https://avatars.githubusercontent.com/u/31716295?v=4",
      "gravatar_id": "",
      "url": "https://api.github.com/users/ferrata",
      "html_url": "https://github.com/ferrata",
      "followers_url": "https://api.github.com/users/ferrata/followers",
      "following_url": "https://api.github.com/users/ferrata/following{/other_user}",
      "gists_url": "https://api.github.com/users/ferrata/gists{/gist_id}",
      "starred_url": "https://api.github.com/users/ferrata/starred{/owner}{/repo}",
      "subscriptions_url": "https://api.github.com/users/ferrata/subscriptions",
      "organizations_url": "https://api.github.com/users/ferrata/orgs",
      "repos_url": "https://api.github.com/users/ferrata/repos",
      "events_url": "https://api.github.com/users/ferrata/events{/privacy}",
      "received_events_url": "https://api.github.com/users/ferrata/received_events",
      "type": "User",
      "user_view_type": "public",
      "site_admin": false
    },
    "truncated": false
  },
  {
    "url": "https://api.github.com/gists/db996efe51d9da878b75ca1de8a3de37",
    "forks_url": "https://api.github.com/gists/db996efe51d9da878b75ca1de8a3de37/forks",
    "commits_url": "https://api.github.com/gists/db996efe51d9da878b75ca1de8a3de37/commits",
    "id": "db996efe51d9da878b75ca1de8a3de37",
    "node_id": "G_kwDOAMtIpNoAIGRiOTk2ZWZlNTFkOWRhODc4Yjc1Y2ExZGU4YTNkZTM3",
    "git_pull_url": "https://gist.github.com/db996efe51d9da878b75ca1de8a3de37.git",
    "git_push_url": "https://gist.github.com/db996efe51d9da878b75ca1de8a3de37.git",
    "html_url": "https://gist.github.com/jyacomp/db996efe51d9da878b75ca1de8a3de37",
    "files": {
      "00-README.md": {
        "filename": "00-README.md",
        "type": "text/markdown",
        "language": "Markdown",
        "raw_url": "https://gist.githubusercontent.com/jyacomp/db996efe51d9da878b75ca1de8a3de37/raw/bb3382ae5830ce6f6ecba2c6aede6310f853d932/00-README.md",
        "size": 1021
      },
      "01-app.py": {
        "filename": "01-app.py",
        "type": "application/x-python",
        "language": "Python",
        "raw_url": "https://gist.githubusercontent.com/jyacomp/db996efe51d9da878b75ca1de8a3de37/raw/5fb816bbd7bb0c7ae04f5928d11db994eb2cfd47/01-app.py",
        "size": 385
      },
      "02-templates-index.html": {
        "filename": "02-templates-index.html",
        "type": "text/html",
        "language": "HTML",
        "raw_url": "https://gist.githubusercontent.com/jyacomp/db996efe51d9da878b75ca1de8a3de37/raw/74158d917b17061c91292908303f449b970087e6/02-templates-index.html",
        "size": 448
      }
    },
    "public": true,
    "created_at": "2025-11-20T21:17:53Z",
    "updated_at": "2025-11-20T21:17:53Z",
    "description": "Information Security | Cross-Site Scripting (XSS) | Flask ",
    "comments": 0,
    "user": null,
    "comments_enabled": true,
    "comments_url": "https://api.github.com/gists/db996efe51d9da878b75ca1de8a3de37/comments",
    "owner": {
      "login": "jyacomp",
      "id": 13322404,
      "node_id": "MDQ6VXNlcjEzMzIyNDA0",
      "avatar_url": "https://avatars.githubusercontent.com/u/13322404?v=4",
      "gravatar_id": "",
      "url": "https://api.github.com/users/jyacomp",
      "html_url": "https://github.com/jyacomp",
      "followers_url": "https://api.github.com/users/jyacomp/followers",
      "following_url": "https://api.github.com/users/jyacomp/following{/other_user}",
      "gists_url": "https://api.github.com/users/jyacomp/gists{/gist_id}",
      "starred_url": "https://api.github.com/users/jyacomp/starred{/owner}{/repo}",
      "subscriptions_url": "https://api.github.com/users/jyacomp/subscriptions",
      "organizations_url": "https://api.github.com/users/jyacomp/orgs",
      "repos_url": "https://api.github.com/users/jyacomp/repos",
      "events_url": "https://api.github.com/users/jyacomp/events{/privacy}",
      "received_events_url": "https://api.github.com/users/jyacomp/received_events",
      "type": "User",
      "user_view_type": "public",
      "site_admin": false
    },
    "truncated": false
  },
  {
    "url": "https://api.github.com/gists/63895152b28205e7ea76c1970fe30cae",
    "forks_url": "https://api.github.com/gists/63895152b28205e7ea76c1970fe30cae/forks",
    "commits_url": "https://api.github.com/gists/63895152b28205e7ea76c1970fe30cae/commits",
    "id": "63895152b28205e7ea76c1970fe30cae",
    "node_id": "G_kwDOC2aY0doAIDYzODk1MTUyYjI4MjA1ZTdlYTc2YzE5NzBmZTMwY2Fl",
    "git_pull_url": "https://gist.github.com/63895152b28205e7ea76c1970fe30cae.git",
    "git_push_url": "https://gist.github.com/63895152b28205e7ea76c1970fe30cae.git",
    "html_url": "https://gist.github.com/vishalmsawant/63895152b28205e7ea76c1970fe30cae",
    "files": {
      "report.html": {
        "filename": "report.html",
        "type": "text/html",
        "language": "HTML",
        "raw_url": "https://gist.githubusercontent.com/vishalmsawant/63895152b28205e7ea76c1970fe30cae/raw/3f0c41c715ae8ce32d17b3cc6fa2e3f5d1e0065d/report.html",
        "size": 62436
      }
    },
    "public": true,
    "created_at": "2025-11-20T21:17:45Z",
    "updated_at": "2025-11-20T21:17:45Z",
    "description": "Automated HTML Report",
    "comments": 0,
    "user": null,
    "comments_enabled": true,
    "comments_url": "https://api.github.com/gists/63895152b28205e7ea76c1970fe30cae/comments",
    "owner": {
      "login": "vishalmsawant",
      "id": 191273169,
      "node_id": "U_kgDOC2aY0Q",
      "avatar_url": "https://avatars.githubusercontent.com/u/191273169?v=4",
      "gravatar_id": "",
      "url": "https://api.github.com/users/vishalmsawant",
      "html_url": "https://github.com/vishalmsawant",
      "followers_url": "https://api.github.com/users/vishalmsawant/followers",
      "following_url": "https://api.github.com/users/vishalmsawant/following{/other_user}",
      "gists_url": "https://api.github.com/users/vishalmsawant/gists{/gist_id}",
      "starred_url": "https://api.github.com/users/vishalmsawant/starred{/owner}{/repo}",
      "subscriptions_url": "https://api.github.com/users/vishalmsawant/subscriptions",
      "organizations_url": "https://api.github.com/users/vishalmsawant/orgs",
      "repos_url": "https://api.github.com/users/vishalmsawant/repos",
      "events_url": "https://api.github.com/users/vishalmsawant/events{/privacy}",
      "received_events_url": "https://api.github.com/users/vishalmsawant/received_events",
      "type": "User",
      "user_view_type": "public",
      "site_admin": false
    },
    "truncated": false
  },
  {
    "url": "https://api.github.com/gists/75ce4176f73181302c570fa3a5c8b2b1",
    "forks_url": "https://api.github.com/gists/75ce4176f73181302c570fa3a5c8b2b1/forks",
    "commits_url": "https://api.github.com/gists/75ce4176f73181302c570fa3a5c8b2b1/commits",
    "id": "75ce4176f73181302c570fa3a5c8b2b1",
    "node_id": "G_kwDOC67RKNoAIDc1Y2U0MTc2ZjczMTgxMzAyYzU3MGZhM2E1YzhiMmIx",
    "git_pull_url": "https://gist.github.com/75ce4176f73181302c570fa3a5c8b2b1.git",
    "git_push_url": "https://gist.github.com/75ce4176f73181302c570fa3a5c8b2b1.git",
    "html_url": "https://gist.github.com/Kamaukari/75ce4176f73181302c570fa3a5c8b2b1",
    "files": {
      "Web untuk edit Foto menjadi HD": {
        "filename": "Web untuk edit Foto menjadi HD",
        "type": "text/plain",
        "language": null,
        "raw_url": "https://gist.githubusercontent.com/Kamaukari/75ce4176f73181302c570fa3a5c8b2b1/raw/7832dc36defec0cf2f5b4d1bb57d15710832d627/Web%20untuk%20edit%20Foto%20menjadi%20HD",
        "size": 1692
      }
    },
    "public": true,
    "created_at": "2025-11-20T21:16:54Z",
    "updated_at": "2025-11-20T21:16:54Z",
    "description": "Fito",
    "comments": 0,
    "user": null,
    "comments_enabled": true,
    "comments_url": "https://api.github.com/gists/75ce4176f73181302c570fa3a5c8b2b1/comments",
    "owner": {
      "login": "Kamaukari",
      "id": 196006184,
      "node_id": "U_kgDOC67RKA",
      "avatar_url": "https://avatars.githubusercontent.com/u/196006184?v=4",
      "gravatar_id": "",
      "url": "https://api.github.com/users/Kamaukari",
      "html_url": "https://github.com/Kamaukari",
      "followers_url": "https://api.github.com/users/Kamaukari/followers",
      "following_url": "https://api.github.com/users/Kamaukari/following{/other_user}",
      "gists_url": "https://api.github.com/users/Kamaukari/gists{/gist_id}",
      "starred_url": "https://api.github.com/users/Kamaukari/starred{/owner}{/repo}",
      "subscriptions_url": "https://api.github.com/users/Kamaukari/subscriptions",
      "organizations_url": "https://api.github.com/users/Kamaukari/orgs",
      "repos_url": "https://api.github.com/users/Kamaukari/repos",
      "events_url": "https://api.github.com/users/Kamaukari/events{/privacy}",
      "received_events_url": "https://api.github.com/users/Kamaukari/received_events",
      "type": "User",
      "user_view_type": "public",
      "site_admin": false
    },
    "truncated": false
  },
  {
    "url": "https://api.github.com/gists/75b44da15757b30023978eb24c75ed70",
    "forks_url": "https://api.github.com/gists/75b44da15757b30023978eb24c75ed70/forks",
    "commits_url": "https://api.github.com/gists/75b44da15757b30023978eb24c75ed70/commits",
    "id": "75b44da15757b30023978eb24c75ed70",
    "node_id": "G_kwDODhWuv9oAIDc1YjQ0ZGExNTc1N2IzMDAyMzk3OGViMjRjNzVlZDcw",
    "git_pull_url": "https://gist.github.com/75b44da15757b30023978eb24c75ed70.git",
    "git_push_url": "https://gist.github.com/75b44da15757b30023978eb24c75ed70.git",
    "html_url": "https://gist.github.com/intanfitriarahmawati/75b44da15757b30023978eb24c75ed70",
    "files": {
      "index.html": {
        "filename": "index.html",
        "type": "text/html",
        "language": "HTML",
        "raw_url": "https://gist.githubusercontent.com/intanfitriarahmawati/75b44da15757b30023978eb24c75ed70/raw/7c82d242c602f2c6c990c58f7e45b1b6db51eead/index.html",
        "size": 7993
      },
      "script.js": {
        "filename": "script.js",
        "type": "text/javascript",
        "language": "JavaScript",
        "raw_url": "https://gist.githubusercontent.com/intanfitriarahmawati/75b44da15757b30023978eb24c75ed70/raw/89cf46e34660c34641ea76b9dabcf7f0c78b287a/script.js",
        "size": 19158
      },
      "style.css": {
        "filename": "style.css",
        "type": "text/css",
        "language": "CSS",
        "raw_url": "https://gist.githubusercontent.com/intanfitriarahmawati/75b44da15757b30023978eb24c75ed70/raw/c593b40bb59a9dc1b957b697fc96e11cf2be8eae/style.css",
        "size": 8591
      },
      "web-belajar-untuk-disleksia.markdown": {
        "filename": "web-belajar-untuk-disleksia.markdown",
        "type": "text/markdown",
        "language": "Markdown",
        "raw_url": "https://gist.githubusercontent.com/intanfitriarahmawati/75b44da15757b30023978eb24c75ed70/raw/46bfb7e7e1d9d74cbb5e68df5122f79f4d562e7a/web-belajar-untuk-disleksia.markdown",
        "size": 242
      }
    },
    "public": true,
    "created_at": "2025-11-20T21:15:37Z",
    "updated_at": "2025-11-20T21:15:37Z",
    "description": "Web Belajar untuk Disleksia",
    "comments": 0,
    "user": null,
    "comments_enabled": true,
    "comments_url": "https://api.github.com/gists/75b44da15757b30023978eb24c75ed70/comments",
    "owner": {
      "login": "intanfitriarahmawati",
      "id": 236302015,
      "node_id": "U_kgDODhWuvw",
      "avatar_url": "https://avatars.githubusercontent.com/u/236302015?v=4",
      "gravatar_id": "",
      "url": "https://api.github.com/users/intanfitriarahmawati",
      "html_url": "https://github.com/intanfitriarahmawati",
      "followers_url": "https://api.github.com/users/intanfitriarahmawati/followers",
      "following_url": "https://api.github.com/users/intanfitriarahmawati/following{/other_user}",
      "gists_url": "https://api.github.com/users/intanfitriarahmawati/gists{/gist_id}",
      "starred_url": "https://api.github.com/users/intanfitriarahmawati/starred{/owner}{/repo}",
      "subscriptions_url": "https://api.github.com/users/intanfitriarahmawati/subscriptions",
      "organizations_url": "https://api.github.com/users/intanfitriarahmawati/orgs",
      "repos_url": "https://api.github.com/users/intanfitriarahmawati/repos",
      "events_url": "https://api.github.com/users/intanfitriarahmawati/events{/privacy}",
      "received_events_url": "https://api.github.com/users/intanfitriarahmawati/received_events",
      "type": "User",
      "user_view_type": "public",
      "site_admin": false
    },
    "truncated": false
  },
  {
    "url": "https://api.github.com/gists/4a53904ea654daeca0ca8e6123efd93b",
    "forks_url": "https://api.github.com/gists/4a53904ea654daeca0ca8e6123efd93b/forks",
    "commits_url": "https://api.github.com/gists/4a53904ea654daeca0ca8e6123efd93b/commits",
    "id": "4a53904ea654daeca0ca8e6123efd93b",
    "node_id": "G_kwDODIr7SdoAIDRhNTM5MDRlYTY1NGRhZWNhMGNhOGU2MTIzZWZkOTNi",
    "git_pull_url": "https://gist.github.com/4a53904ea654daeca0ca8e6123efd93b.git",
    "git_push_url": "https://gist.github.com/4a53904ea654daeca0ca8e6123efd93b.git",
    "html_url": "https://gist.github.com/RochesterNHScannerAlertsMediaGroup/4a53904ea654daeca0ca8e6123efd93b",
    "files": {
      "ALERT": {
        "filename": "ALERT",
        "type": "text/plain",
        "language": null,
        "raw_url": "https://gist.githubusercontent.com/RochesterNHScannerAlertsMediaGroup/4a53904ea654daeca0ca8e6123efd93b/raw/fc6a3415b9fe27d2637a0b3f2b8fcce6d0bf25a9/ALERT",
        "size": 123
      }
    },
    "public": true,
    "created_at": "2025-11-20T21:15:34Z",
    "updated_at": "2025-11-20T21:15:34Z",
    "description": "RECENT ALERT",
    "comments": 0,
    "user": null,
    "comments_enabled": true,
    "comments_url": "https://api.github.com/gists/4a53904ea654daeca0ca8e6123efd93b/comments",
    "owner": {
      "login": "RochesterNHScannerAlertsMediaGroup",
      "id": 210434889,
      "node_id": "U_kgDODIr7SQ",
      "avatar_url": "https://avatars.githubusercontent.com/u/210434889?v=4",
      "gravatar_id": "",
      "url": "https://api.github.com/users/RochesterNHScannerAlertsMediaGroup",
      "html_url": "https://github.com/RochesterNHScannerAlertsMediaGroup",
      "followers_url": "https://api.github.com/users/RochesterNHScannerAlertsMediaGroup/followers",
      "following_url": "https://api.github.com/users/RochesterNHScannerAlertsMediaGroup/following{/other_user}",
      "gists_url": "https://api.github.com/users/RochesterNHScannerAlertsMediaGroup/gists{/gist_id}",
      "starred_url": "https://api.github.com/users/RochesterNHScannerAlertsMediaGroup/starred{/owner}{/repo}",
      "subscriptions_url": "https://api.github.com/users/RochesterNHScannerAlertsMediaGroup/subscriptions",
      "organizations_url": "https://api.github.com/users/RochesterNHScannerAlertsMediaGroup/orgs",
      "repos_url": "https://api.github.com/users/RochesterNHScannerAlertsMediaGroup/repos",
      "events_url": "https://api.github.com/users/RochesterNHScannerAlertsMediaGroup/events{/privacy}",
      "received_events_url": "https://api.github.com/users/RochesterNHScannerAlertsMediaGroup/received_events",
      "type": "User",
      "user_view_type": "public",
      "site_admin": false
    },
    "truncated": false
  },
  {
    "url": "https://api.github.com/gists/7bc63207d368198ae0a3584c6d99b799",
    "forks_url": "https://api.github.com/gists/7bc63207d368198ae0a3584c6d99b799/forks",
    "commits_url": "https://api.github.com/gists/7bc63207d368198ae0a3584c6d99b799/commits",
    "id": "7bc63207d368198ae0a3584c6d99b799",
    "node_id": "G_kwDOBUWb_doAIDdiYzYzMjA3ZDM2ODE5OGFlMGEzNTg0YzZkOTliNzk5",
    "git_pull_url": "https://gist.github.com/7bc63207d368198ae0a3584c6d99b799.git",
    "git_push_url": "https://gist.github.com/7bc63207d368198ae0a3584c6d99b799.git",
    "html_url": "https://gist.github.com/rh-operator-bundle-bot/7bc63207d368198ae0a3584c6d99b799",
    "files": {
      "operator-release-pipeline-run5t2sw.log": {
        "filename": "operator-release-pipeline-run5t2sw.log",
        "type": "text/plain",
        "language": null,
        "raw_url": "https://gist.githubusercontent.com/rh-operator-bundle-bot/7bc63207d368198ae0a3584c6d99b799/raw/f002d8f4e7b5d648c63cc46f7154fdb2f57ad240/operator-release-pipeline-run5t2sw.log",
        "size": 882070
      }
    },
    "public": true,
    "created_at": "2025-11-20T21:14:16Z",
    "updated_at": "2025-11-20T21:14:16Z",
    "description": null,
    "comments": 0,
    "user": null,
    "comments_enabled": true,
    "comments_url": "https://api.github.com/gists/7bc63207d368198ae0a3584c6d99b799/comments",
    "owner": {
      "login": "rh-operator-bundle-bot",
      "id": 88447997,
      "node_id": "MDQ6VXNlcjg4NDQ3OTk3",
      "avatar_url": "https://avatars.githubusercontent.com/u/88447997?v=4",
      "gravatar_id": "",
      "url": "https://api.github.com/users/rh-operator-bundle-bot",
      "html_url": "https://github.com/rh-operator-bundle-bot",
      "followers_url": "https://api.github.com/users/rh-operator-bundle-bot/followers",
      "following_url": "https://api.github.com/users/rh-operator-bundle-bot/following{/other_user}",
      "gists_url": "https://api.github.com/users/rh-operator-bundle-bot/gists{/gist_id}",
      "starred_url": "https://api.github.com/users/rh-operator-bundle-bot/starred{/owner}{/repo}",
      "subscriptions_url": "https://api.github.com/users/rh-operator-bundle-bot/subscriptions",
      "organizations_url": "https://api.github.com/users/rh-operator-bundle-bot/orgs",
      "repos_url": "https://api.github.com/users/rh-operator-bundle-bot/repos",
      "events_url": "https://api.github.com/users/rh-operator-bundle-bot/events{/privacy}",
      "received_events_url": "https://api.github.com/users/rh-operator-bundle-bot/received_events",
      "type": "User",
      "user_view_type": "public",
      "site_admin": false
    },
    "truncated": false
  },
  {
    "url": "https://api.github.com/gists/b36579a7df9e0062f093d82f3c93ceb8",
    "forks_url": "https://api.github.com/gists/b36579a7df9e0062f093d82f3c93ceb8/forks",
    "commits_url": "https://api.github.com/gists/b36579a7df9e0062f093d82f3c93ceb8/commits",
    "id": "b36579a7df9e0062f093d82f3c93ceb8",
    "node_id": "G_kwDOAePzx9oAIGIzNjU3OWE3ZGY5ZTAwNjJmMDkzZDgyZjNjOTNjZWI4",
    "git_pull_url": "https://gist.github.com/b36579a7df9e0062f093d82f3c93ceb8.git",
    "git_push_url": "https://gist.github.com/b36579a7df9e0062f093d82f3c93ceb8.git",
    "html_url": "https://gist.github.com/ferrata/b36579a7df9e0062f093d82f3c93ceb8",
    "files": {
      "openapi.yaml": {
        "filename": "openapi.yaml",
        "type": "text/x-yaml",
        "language": "OASv3-yaml",
        "raw_url": "https://gist.githubusercontent.com/ferrata/b36579a7df9e0062f093d82f3c93ceb8/raw/f546b4a8fb932074054b221f797e0736201bc315/openapi.yaml",
        "size": 68187
      }
    },
    "public": true,
    "created_at": "2025-11-20T21:13:57Z",
    "updated_at": "2025-11-20T21:13:57Z",
    "description": "OpenAPI spec for PR #2082",
    "comments": 0,
    "user": null,
    "comments_enabled": true,
    "comments_url": "https://api.github.com/gists/b36579a7df9e0062f093d82f3c93ceb8/comments",
    "owner": {
      "login": "ferrata",
      "id": 31716295,
      "node_id": "MDQ6VXNlcjMxNzE2Mjk1",
      "avatar_url": "https://avatars.githubusercontent.com/u/31716295?v=4",
      "gravatar_id": "",
      "url": "https://api.github.com/users/ferrata",
      "html_url": "https://github.com/ferrata",
      "followers_url": "https://api.github.com/users/ferrata/followers",
      "following_url": "https://api.github.com/users/ferrata/following{/other_user}",
      "gists_url": "https://api.github.com/users/ferrata/gists{/gist_id}",
      "starred_url": "https://api.github.com/users/ferrata/starred{/owner}{/repo}",
      "subscriptions_url": "https://api.github.com/users/ferrata/subscriptions",
      "organizations_url": "https://api.github.com/users/ferrata/orgs",
      "repos_url": "https://api.github.com/users/ferrata/repos",
      "events_url": "https://api.github.com/users/ferrata/events{/privacy}",
      "received_events_url": "https://api.github.com/users/ferrata/received_events",
      "type": "User",
      "user_view_type": "public",
      "site_admin": false
    },
    "truncated": false
  },
  {
    "url": "https://api.github.com/gists/57b9bb46f0e7ffc3c37a578e81d2c17e",
    "forks_url": "https://api.github.com/gists/57b9bb46f0e7ffc3c37a578e81d2c17e/forks",
    "commits_url": "https://api.github.com/gists/57b9bb46f0e7ffc3c37a578e81d2c17e/commits",
    "id": "57b9bb46f0e7ffc3c37a578e81d2c17e",
    "node_id": "G_kwDOCCifQNoAIDU3YjliYjQ2ZjBlN2ZmYzNjMzdhNTc4ZTgxZDJjMTdl",
    "git_pull_url": "https://gist.github.com/57b9bb46f0e7ffc3c37a578e81d2c17e.git",
    "git_push_url": "https://gist.github.com/57b9bb46f0e7ffc3c37a578e81d2c17e.git",
    "html_url": "https://gist.github.com/Rhishavhere/57b9bb46f0e7ffc3c37a578e81d2c17e",
    "files": {
      "gistfile1.txt": {
        "filename": "gistfile1.txt",
        "type": "text/plain",
        "language": "Text",
        "raw_url": "https://gist.githubusercontent.com/Rhishavhere/57b9bb46f0e7ffc3c37a578e81d2c17e/raw/e3d3300fa215b6479f470a901caa0d5ccf28351c/gistfile1.txt",
        "size": 1129
      }
    },
    "public": true,
    "created_at": "2025-11-20T21:13:40Z",
    "updated_at": "2025-11-20T21:13:40Z",
    "description": "",
    "comments": 0,
    "user": null,
    "comments_enabled": true,
    "comments_url": "https://api.github.com/gists/57b9bb46f0e7ffc3c37a578e81d2c17e/comments",
    "owner": {
      "login": "Rhishavhere",
      "id": 136879936,
      "node_id": "U_kgDOCCifQA",
      "avatar_url": "https://avatars.githubusercontent.com/u/136879936?v=4",
      "gravatar_id": "",
      "url": "https://api.github.com/users/Rhishavhere",
      "html_url": "https://github.com/Rhishavhere",
      "followers_url": "https://api.github.com/users/Rhishavhere/followers",
      "following_url": "https://api.github.com/users/Rhishavhere/following{/other_user}",
      "gists_url": "https://api.github.com/users/Rhishavhere/gists{/gist_id}",
      "starred_url": "https://api.github.com/users/Rhishavhere/starred{/owner}{/repo}",
      "subscriptions_url": "https://api.github.com/users/Rhishavhere/subscriptions",
      "organizations_url": "https://api.github.com/users/Rhishavhere/orgs",
      "repos_url": "https://api.github.com/users/Rhishavhere/repos",
      "events_url": "https://api.github.com/users/Rhishavhere/events{/privacy}",
      "received_events_url": "https://api.github.com/users/Rhishavhere/received_events",
      "type": "User",
      "user_view_type": "public",
      "site_admin": false
    },
    "truncated": false
  },
  {
    "url": "https://api.github.com/gists/d398a29a2de1fed8ebedf20eb9a1e0eb",
    "forks_url": "https://api.github.com/gists/d398a29a2de1fed8ebedf20eb9a1e0eb/forks",
    "commits_url": "https://api.github.com/gists/d398a29a2de1fed8ebedf20eb9a1e0eb/commits",
    "id": "d398a29a2de1fed8ebedf20eb9a1e0eb",
    "node_id": "G_kwDOCPZ7ZdoAIGQzOThhMjlhMmRlMWZlZDhlYmVkZjIwZWI5YTFlMGVi",
    "git_pull_url": "https://gist.github.com/d398a29a2de1fed8ebedf20eb9a1e0eb.git",
    "git_push_url": "https://gist.github.com/d398a29a2de1fed8ebedf20eb9a1e0eb.git",
    "html_url": "https://gist.github.com/weilian011/d398a29a2de1fed8ebedf20eb9a1e0eb",
    "files": {
      "gistfile1.txt": {
        "filename": "gistfile1.txt",
        "type": "text/plain",
        "language": "Text",
        "raw_url": "https://gist.githubusercontent.com/weilian011/d398a29a2de1fed8ebedf20eb9a1e0eb/raw/96d333692fae5feec5db8df24cd81a610737351b/gistfile1.txt",
        "size": 284859
      }
    },
    "public": true,
    "created_at": "2025-11-20T21:13:35Z",
    "updated_at": "2025-11-20T21:13:36Z",
    "description": "",
    "comments": 0,
    "user": null,
    "comments_enabled": true,
    "comments_url": "https://api.github.com/gists/d398a29a2de1fed8ebedf20eb9a1e0eb/comments",
    "owner": {
      "login": "weilian011",
      "id": 150371173,
      "node_id": "U_kgDOCPZ7ZQ",
      "avatar_url": "https://avatars.githubusercontent.com/u/150371173?v=4",
      "gravatar_id": "",
      "url": "https://api.github.com/users/weilian011",
      "html_url": "https://github.com/weilian011",
      "followers_url": "https://api.github.com/users/weilian011/followers",
      "following_url": "https://api.github.com/users/weilian011/following{/other_user}",
      "gists_url": "https://api.github.com/users/weilian011/gists{/gist_id}",
      "starred_url": "https://api.github.com/users/weilian011/starred{/owner}{/repo}",
      "subscriptions_url": "https://api.github.com/users/weilian011/subscriptions",
      "organizations_url": "https://api.github.com/users/weilian011/orgs",
      "repos_url": "https://api.github.com/users/weilian011/repos",
      "events_url": "https://api.github.com/users/weilian011/events{/privacy}",
      "received_events_url": "https://api.github.com/users/weilian011/received_events",
      "type": "User",
      "user_view_type": "public",
      "site_admin": false
    },
    "truncated": false
  },
  {
    "url": "https://api.github.com/gists/7862b4a45fc23c0d6d3fd1b54bb4a477",
    "forks_url": "https://api.github.com/gists/7862b4a45fc23c0d6d3fd1b54bb4a477/forks",
    "commits_url": "https://api.github.com/gists/7862b4a45fc23c0d6d3fd1b54bb4a477/commits",
    "id": "7862b4a45fc23c0d6d3fd1b54bb4a477",
    "node_id": "G_kwDOAC_7e9oAIDc4NjJiNGE0NWZjMjNjMGQ2ZDNmZDFiNTRiYjRhNDc3",
    "git_pull_url": "https://gist.github.com/7862b4a45fc23c0d6d3fd1b54bb4a477.git",
    "git_push_url": "https://gist.github.com/7862b4a45fc23c0d6d3fd1b54bb4a477.git",
    "html_url": "https://gist.github.com/stpaultim/7862b4a45fc23c0d6d3fd1b54bb4a477",
    "files": {
      "newdropsite.sh": {
        "filename": "newdropsite.sh",
        "type": "application/x-sh",
        "language": "Shell",
        "raw_url": "https://gist.githubusercontent.com/stpaultim/7862b4a45fc23c0d6d3fd1b54bb4a477/raw/8cf7d45511a9d0d248971ed7073f06f358ce17b5/newdropsite.sh",
        "size": 2441
      }
    },
    "public": true,
    "created_at": "2025-11-20T21:13:06Z",
    "updated_at": "2025-11-20T21:13:07Z",
    "description": "Spin up backdrop site with Core PR (optional)",
    "comments": 0,
    "user": null,
    "comments_enabled": true,
    "comments_url": "https://api.github.com/gists/7862b4a45fc23c0d6d3fd1b54bb4a477/comments",
    "owner": {
      "login": "stpaultim",
      "id": 3144571,
      "node_id": "MDQ6VXNlcjMxNDQ1NzE=",
      "avatar_url": "https://avatars.githubusercontent.com/u/3144571?v=4",
      "gravatar_id": "",
      "url": "https://api.github.com/users/stpaultim",
      "html_url": "https://github.com/stpaultim",
      "followers_url": "https://api.github.com/users/stpaultim/followers",
      "following_url": "https://api.github.com/users/stpaultim/following{/other_user}",
      "gists_url": "https://api.github.com/users/stpaultim/gists{/gist_id}",
      "starred_url": "https://api.github.com/users/stpaultim/starred{/owner}{/repo}",
      "subscriptions_url": "https://api.github.com/users/stpaultim/subscriptions",
      "organizations_url": "https://api.github.com/users/stpaultim/orgs",
      "repos_url": "https://api.github.com/users/stpaultim/repos",
      "events_url": "https://api.github.com/users/stpaultim/events{/privacy}",
      "received_events_url": "https://api.github.com/users/stpaultim/received_events",
      "type": "User",
      "user_view_type": "public",
      "site_admin": false
    },
    "truncated": false
  },
  {
    "url": "https://api.github.com/gists/cf7cebf0b08d8c257e687bd61f41e1bd",
    "forks_url": "https://api.github.com/gists/cf7cebf0b08d8c257e687bd61f41e1bd/forks",
    "commits_url": "https://api.github.com/gists/cf7cebf0b08d8c257e687bd61f41e1bd/commits",
    "id": "cf7cebf0b08d8c257e687bd61f41e1bd",
    "node_id": "G_kwDOAK-iytoAIGNmN2NlYmYwYjA4ZDhjMjU3ZTY4N2JkNjFmNDFlMWJk",
    "git_pull_url": "https://gist.github.com/cf7cebf0b08d8c257e687bd61f41e1bd.git",
    "git_push_url": "https://gist.github.com/cf7cebf0b08d8c257e687bd61f41e1bd.git",
    "html_url": "https://gist.github.com/TheArchitectEngineer/cf7cebf0b08d8c257e687bd61f41e1bd",
    "files": {
      "repo-rinse.sh": {
        "filename": "repo-rinse.sh",
        "type": "application/x-sh",
        "language": "Shell",
        "raw_url": "https://gist.githubusercontent.com/TheArchitectEngineer/cf7cebf0b08d8c257e687bd61f41e1bd/raw/0461298f1e450c0d85ba856ca77b22f10a0444ef/repo-rinse.sh",
        "size": 172
      }
    },
    "public": true,
    "created_at": "2025-11-20T21:12:42Z",
    "updated_at": "2025-11-20T21:12:42Z",
    "description": "Cleans and resets a git repo and its submodules",
    "comments": 0,
    "user": null,
    "comments_enabled": true,
    "comments_url": "https://api.github.com/gists/cf7cebf0b08d8c257e687bd61f41e1bd/comments",
    "owner": {
      "login": "TheArchitectEngineer",
      "id": 11510474,
      "node_id": "MDQ6VXNlcjExNTEwNDc0",
      "avatar_url": "https://avatars.githubusercontent.com/u/11510474?v=4",
      "gravatar_id": "",
      "url": "https://api.github.com/users/TheArchitectEngineer",
      "html_url": "https://github.com/TheArchitectEngineer",
      "followers_url": "https://api.github.com/users/TheArchitectEngineer/followers",
      "following_url": "https://api.github.com/users/TheArchitectEngineer/following{/other_user}",
      "gists_url": "https://api.github.com/users/TheArchitectEngineer/gists{/gist_id}",
      "starred_url": "https://api.github.com/users/TheArchitectEngineer/starred{/owner}{/repo}",
      "subscriptions_url": "https://api.github.com/users/TheArchitectEngineer/subscriptions",
      "organizations_url": "https://api.github.com/users/TheArchitectEngineer/orgs",
      "repos_url": "https://api.github.com/users/TheArchitectEngineer/repos",
      "events_url": "https://api.github.com/users/TheArchitectEngineer/events{/privacy}",
      "received_events_url": "https://api.github.com/users/TheArchitectEngineer/received_events",
      "type": "User",
      "user_view_type": "public",
      "site_admin": false
    },
    "truncated": false
  },
  {
    "url": "https://api.github.com/gists/2775b0ee8dbd50d4cd7fe80d6ae6406d",
    "forks_url": "https://api.github.com/gists/2775b0ee8dbd50d4cd7fe80d6ae6406d/forks",
    "commits_url": "https://api.github.com/gists/2775b0ee8dbd50d4cd7fe80d6ae6406d/commits",
    "id": "2775b0ee8dbd50d4cd7fe80d6ae6406d",
    "node_id": "G_kwDOBJPWStoAIDI3NzViMGVlOGRiZDUwZDRjZDdmZTgwZDZhZTY0MDZk",
    "git_pull_url": "https://gist.github.com/2775b0ee8dbd50d4cd7fe80d6ae6406d.git",
    "git_push_url": "https://gist.github.com/2775b0ee8dbd50d4cd7fe80d6ae6406d.git",
    "html_url": "https://gist.github.com/sholajapheth/2775b0ee8dbd50d4cd7fe80d6ae6406d",
    "files": {
      ".git...HEAD": {
        "filename": ".git...HEAD",
        "type": "text/plain",
        "language": null,
        "raw_url": "https://gist.githubusercontent.com/sholajapheth/2775b0ee8dbd50d4cd7fe80d6ae6406d/raw/b870d82622c1a9ca6bcaf5df639680424a1904b0/.git...HEAD",
        "size": 21
      },
      ".git...config": {
        "filename": ".git...config",
        "type": "text/plain",
        "language": null,
        "raw_url": "https://gist.githubusercontent.com/sholajapheth/2775b0ee8dbd50d4cd7fe80d6ae6406d/raw/d545cdabdbddafca3501d2114506fc86e50e9824/.git...config",
        "size": 130
      },
      ".git...index": {
        "filename": ".git...index",
        "type": "text/plain",
        "language": null,
        "raw_url": "https://gist.githubusercontent.com/sholajapheth/2775b0ee8dbd50d4cd7fe80d6ae6406d/raw/49f7b918301008222b7d6cfd38a64d6383ab60a3/.git...index",
        "size": 1194
      },
      ".git...objects...13...efec6eef33e76b98f3959e73203ff3c8933f9d": {
        "filename": ".git...objects...13...efec6eef33e76b98f3959e73203ff3c8933f9d",
        "type": "text/plain",
        "language": null,
        "raw_url": "https://gist.githubusercontent.com/sholajapheth/2775b0ee8dbd50d4cd7fe80d6ae6406d/raw/e75f7ab60611e19734887a7b48b802011f854f64/.git...objects...13...efec6eef33e76b98f3959e73203ff3c8933f9d",
        "size": 219
      },
      ".git...objects...22...35c2878ce2abc44486d9d07e3ba4db6e5a4f71": {
        "filename": ".git...objects...22...35c2878ce2abc44486d9d07e3ba4db6e5a4f71",
        "type": "text/plain",
        "language": null,
        "raw_url": "https://gist.githubusercontent.com/sholajapheth/2775b0ee8dbd50d4cd7fe80d6ae6406d/raw/71148a2ebb19050cfb14fbd1007d648e4e47bc18/.git...objects...22...35c2878ce2abc44486d9d07e3ba4db6e5a4f71",
        "size": 170
      },
      ".git...objects...49...146e99facba02fce64738239bec0b835cec15b": {
        "filename": ".git...objects...49...146e99facba02fce64738239bec0b835cec15b",
        "type": "text/plain",
        "language": null,
        "raw_url": "https://gist.githubusercontent.com/sholajapheth/2775b0ee8dbd50d4cd7fe80d6ae6406d/raw/253a1a565a802c6ad3ffafc4c258443c36068f65/.git...objects...49...146e99facba02fce64738239bec0b835cec15b",
        "size": 775
      },
      ".git...objects...4b...936e9ee108c03a9212f848522aa0ba35e9f789": {
        "filename": ".git...objects...4b...936e9ee108c03a9212f848522aa0ba35e9f789",
        "type": "text/plain",
        "language": null,
        "raw_url": "https://gist.githubusercontent.com/sholajapheth/2775b0ee8dbd50d4cd7fe80d6ae6406d/raw/0db677b849cf932a4ab3ce5c24ca2705c6d8773d/.git...objects...4b...936e9ee108c03a9212f848522aa0ba35e9f789",
        "size": 1402
      },
      ".git...objects...51...3d496d7638a86e7b7339272f853a7053429336": {
        "filename": ".git...objects...51...3d496d7638a86e7b7339272f853a7053429336",
        "type": "text/plain",
        "language": "Roff",
        "raw_url": "https://gist.githubusercontent.com/sholajapheth/2775b0ee8dbd50d4cd7fe80d6ae6406d/raw/218762829ba89d6bb96353c9c777ad4664c1157a/.git...objects...51...3d496d7638a86e7b7339272f853a7053429336",
        "size": 564
      },
      ".git...objects...56...b215955168a0867388822328104604acdf0772": {
        "filename": ".git...objects...56...b215955168a0867388822328104604acdf0772",
        "type": "text/plain",
        "language": null,
        "raw_url": "https://gist.githubusercontent.com/sholajapheth/2775b0ee8dbd50d4cd7fe80d6ae6406d/raw/2f828c535606f27cf630a9d47dcf5b9e636f4941/.git...objects...56...b215955168a0867388822328104604acdf0772",
        "size": 3828
      },
      ".git...objects...59...f67d5bca25cae42da9d0449a997ec4d617abcd": {
        "filename": ".git...objects...59...f67d5bca25cae42da9d0449a997ec4d617abcd",
        "type": "text/plain",
        "language": null,
        "raw_url": "https://gist.githubusercontent.com/sholajapheth/2775b0ee8dbd50d4cd7fe80d6ae6406d/raw/e1537321d085be72ad37f8a332c61a60eebccca4/.git...objects...59...f67d5bca25cae42da9d0449a997ec4d617abcd",
        "size": 149
      },
      ".git...objects...7a...ff9aa3d5c2ac9eec1add0101a061835c056998": {
        "filename": ".git...objects...7a...ff9aa3d5c2ac9eec1add0101a061835c056998",
        "type": "text/plain",
        "language": null,
        "raw_url": "https://gist.githubusercontent.com/sholajapheth/2775b0ee8dbd50d4cd7fe80d6ae6406d/raw/52797a63b32a3da79702dc3ef1ed98d9c745e04f/.git...objects...7a...ff9aa3d5c2ac9eec1add0101a061835c056998",
        "size": 1377
      },
      ".git...objects...8c...a683a2173785a5b619b06a5dbd4c5ef432bbde": {
        "filename": ".git...objects...8c...a683a2173785a5b619b06a5dbd4c5ef432bbde",
        "type": "text/plain",
        "language": null,
        "raw_url": "https://gist.githubusercontent.com/sholajapheth/2775b0ee8dbd50d4cd7fe80d6ae6406d/raw/a8abb0e7d876f89fcc62c0bc0b4d8b7725998736/.git...objects...8c...a683a2173785a5b619b06a5dbd4c5ef432bbde",
        "size": 197
      },
      ".git...objects...8e...37b7c39b76b12519a9f931ba858624e573e1f7": {
        "filename": ".git...objects...8e...37b7c39b76b12519a9f931ba858624e573e1f7",
        "type": "text/plain",
        "language": null,
        "raw_url": "https://gist.githubusercontent.com/sholajapheth/2775b0ee8dbd50d4cd7fe80d6ae6406d/raw/55d70480d19a99325de42bbe1a019be8daad183c/.git...objects...8e...37b7c39b76b12519a9f931ba858624e573e1f7",
        "size": 674
      },
      ".git...objects...b2...a56f23717b4b9b8f05d45363a0fd58c657ce6e": {
        "filename": ".git...objects...b2...a56f23717b4b9b8f05d45363a0fd58c657ce6e",
        "type": "text/plain",
        "language": null,
        "raw_url": "https://gist.githubusercontent.com/sholajapheth/2775b0ee8dbd50d4cd7fe80d6ae6406d/raw/ce86319a1c3679b000388b03fcc9e6bc34274dd9/.git...objects...b2...a56f23717b4b9b8f05d45363a0fd58c657ce6e",
        "size": 338
      },
      ".git...objects...c5...dd03f7deb6a05afaadcd8218bdbcc41e571d5a": {
        "filename": ".git...objects...c5...dd03f7deb6a05afaadcd8218bdbcc41e571d5a",
        "type": "text/plain",
        "language": null,
        "raw_url": "https://gist.githubusercontent.com/sholajapheth/2775b0ee8dbd50d4cd7fe80d6ae6406d/raw/49e9476155927e6d3ff46b1ba5da53fa0cfe4a37/.git...objects...c5...dd03f7deb6a05afaadcd8218bdbcc41e571d5a",
        "size": 1112
      },
      ".git...objects...db...51c0094e32edbb6f883126ba260296f9f93ec5": {
        "filename": ".git...objects...db...51c0094e32edbb6f883126ba260296f9f93ec5",
        "type": "text/plain",
        "language": null,
        "raw_url": "https://gist.githubusercontent.com/sholajapheth/2775b0ee8dbd50d4cd7fe80d6ae6406d/raw/bf681d5301b2eb53cb66366b8bde7b355b7f4873/.git...objects...db...51c0094e32edbb6f883126ba260296f9f93ec5",
        "size": 436
      },
      ".git...objects...dd...1e15d25e783b6eb2149c024787678c663616f7": {
        "filename": ".git...objects...dd...1e15d25e783b6eb2149c024787678c663616f7",
        "type": "text/plain",
        "language": "Roff",
        "raw_url": "https://gist.githubusercontent.com/sholajapheth/2775b0ee8dbd50d4cd7fe80d6ae6406d/raw/da5cb2197c933a5a264abf3da7add09bb3ab316d/.git...objects...dd...1e15d25e783b6eb2149c024787678c663616f7",
        "size": 578
      },
      ".git...objects...ea...d4737ad684660889f2c6f2bda473d2fa31e6f3": {
        "filename": ".git...objects...ea...d4737ad684660889f2c6f2bda473d2fa31e6f3",
        "type": "text/plain",
        "language": null,
        "raw_url": "https://gist.githubusercontent.com/sholajapheth/2775b0ee8dbd50d4cd7fe80d6ae6406d/raw/4d5660ee1d7173800c14bc21a51eacca826ed0f1/.git...objects...ea...d4737ad684660889f2c6f2bda473d2fa31e6f3",
        "size": 171
      },
      ".git...refs...heads...main": {
        "filename": ".git...refs...heads...main",
        "type": "text/plain",
        "language": null,
        "raw_url": "https://gist.githubusercontent.com/sholajapheth/2775b0ee8dbd50d4cd7fe80d6ae6406d/raw/8cbf94e5f5cca7c53e4f82aae2ef439bc346b39a/.git...refs...heads...main",
        "size": 41
      },
      ".prettierrc.json": {
        "filename": ".prettierrc.json",
        "type": "application/json",
        "language": "JSON",
        "raw_url": "https://gist.githubusercontent.com/sholajapheth/2775b0ee8dbd50d4cd7fe80d6ae6406d/raw/b2a56f23717b4b9b8f05d45363a0fd58c657ce6e/.prettierrc.json",
        "size": 758
      },
      "README.txt": {
        "filename": "README.txt",
        "type": "text/plain",
        "language": "Text",
        "raw_url": "https://gist.githubusercontent.com/sholajapheth/2775b0ee8dbd50d4cd7fe80d6ae6406d/raw/4b936e9ee108c03a9212f848522aa0ba35e9f789/README.txt",
        "size": 1494
      },
      "contracts...1_Storage.sol": {
        "filename": "contracts...1_Storage.sol",
        "type": "text/plain",
        "language": "Solidity",
        "raw_url": "https://gist.githubusercontent.com/sholajapheth/2775b0ee8dbd50d4cd7fe80d6ae6406d/raw/dd1e15d25e783b6eb2149c024787678c663616f7/contracts...1_Storage.sol",
        "size": 555
      },
      "contracts...2_Owner.sol": {
        "filename": "contracts...2_Owner.sol",
        "type": "text/plain",
        "language": "Solidity",
        "raw_url": "https://gist.githubusercontent.com/sholajapheth/2775b0ee8dbd50d4cd7fe80d6ae6406d/raw/7aff9aa3d5c2ac9eec1add0101a061835c056998/contracts...2_Owner.sol",
        "size": 1652
      },
      "contracts...3_Ballot.sol": {
        "filename": "contracts...3_Ballot.sol",
        "type": "text/plain",
        "language": "Solidity",
        "raw_url": "https://gist.githubusercontent.com/sholajapheth/2775b0ee8dbd50d4cd7fe80d6ae6406d/raw/56b215955168a0867388822328104604acdf0772/contracts...3_Ballot.sol",
        "size": 6216
      },
      "remix.config.json": {
        "filename": "remix.config.json",
        "type": "application/json",
        "language": "JSON",
        "raw_url": "https://gist.githubusercontent.com/sholajapheth/2775b0ee8dbd50d4cd7fe80d6ae6406d/raw/59f67d5bca25cae42da9d0449a997ec4d617abcd/remix.config.json",
        "size": 84
      },
      "scripts...deploy_with_ethers.ts": {
        "filename": "scripts...deploy_with_ethers.ts",
        "type": "video/MP2T",
        "language": "TypeScript",
        "raw_url": "https://gist.githubusercontent.com/sholajapheth/2775b0ee8dbd50d4cd7fe80d6ae6406d/raw/513d496d7638a86e7b7339272f853a7053429336/scripts...deploy_with_ethers.ts",
        "size": 488
      },
      "scripts...ethers-lib.ts": {
        "filename": "scripts...ethers-lib.ts",
        "type": "video/MP2T",
        "language": "TypeScript",
        "raw_url": "https://gist.githubusercontent.com/sholajapheth/2775b0ee8dbd50d4cd7fe80d6ae6406d/raw/c5dd03f7deb6a05afaadcd8218bdbcc41e571d5a/scripts...ethers-lib.ts",
        "size": 1227
      },
      "tests...Ballot_test.sol": {
        "filename": "tests...Ballot_test.sol",
        "type": "text/plain",
        "language": "Solidity",
        "raw_url": "https://gist.githubusercontent.com/sholajapheth/2775b0ee8dbd50d4cd7fe80d6ae6406d/raw/49146e99facba02fce64738239bec0b835cec15b/tests...Ballot_test.sol",
        "size": 938
      },
      "tests...storage.test.js": {
        "filename": "tests...storage.test.js",
        "type": "text/javascript",
        "language": "JavaScript",
        "raw_url": "https://gist.githubusercontent.com/sholajapheth/2775b0ee8dbd50d4cd7fe80d6ae6406d/raw/8e37b7c39b76b12519a9f931ba858624e573e1f7/tests...storage.test.js",
        "size": 947
      }
    },
    "public": true,
    "created_at": "2025-11-20T21:12:40Z",
    "updated_at": "2025-11-20T21:12:41Z",
    "description": "Created using remix-ide: Realtime Ethereum Contract Compiler and Runtime. \n Load this file by pasting this gists URL or ID at https://remix.ethereum.org/#version=soljson-v0.8.24+commit.e11b9ed9.js&optimize=undefined&runs=200&gist=",
    "comments": 0,
    "user": null,
    "comments_enabled": true,
    "comments_url": "https://api.github.com/gists/2775b0ee8dbd50d4cd7fe80d6ae6406d/comments",
    "owner": {
      "login": "sholajapheth",
      "id": 76797514,
      "node_id": "MDQ6VXNlcjc2Nzk3NTE0",
      "avatar_url": "https://avatars.githubusercontent.com/u/76797514?v=4",
      "gravatar_id": "",
      "url": "https://api.github.com/users/sholajapheth",
      "html_url": "https://github.com/sholajapheth",
      "followers_url": "https://api.github.com/users/sholajapheth/followers",
      "following_url": "https://api.github.com/users/sholajapheth/following{/other_user}",
      "gists_url": "https://api.github.com/users/sholajapheth/gists{/gist_id}",
      "starred_url": "https://api.github.com/users/sholajapheth/starred{/owner}{/repo}",
      "subscriptions_url": "https://api.github.com/users/sholajapheth/subscriptions",
      "organizations_url": "https://api.github.com/users/sholajapheth/orgs",
      "repos_url": "https://api.github.com/users/sholajapheth/repos",
      "events_url": "https://api.github.com/users/sholajapheth/events{/privacy}",
      "received_events_url": "https://api.github.com/users/sholajapheth/received_events",
      "type": "User",
      "user_view_type": "public",
      "site_admin": false
    },
    "truncated": false
  },
  {
    "url": "https://api.github.com/gists/1d1b5c2688c9726d5343bbaddd315ec9",
    "forks_url": "https://api.github.com/gists/1d1b5c2688c9726d5343bbaddd315ec9/forks",
    "commits_url": "https://api.github.com/gists/1d1b5c2688c9726d5343bbaddd315ec9/commits",
    "id": "1d1b5c2688c9726d5343bbaddd315ec9",
    "node_id": "G_kwDOC2aY0doAIDFkMWI1YzI2ODhjOTcyNmQ1MzQzYmJhZGRkMzE1ZWM5",
    "git_pull_url": "https://gist.github.com/1d1b5c2688c9726d5343bbaddd315ec9.git",
    "git_push_url": "https://gist.github.com/1d1b5c2688c9726d5343bbaddd315ec9.git",
    "html_url": "https://gist.github.com/vishalmsawant/1d1b5c2688c9726d5343bbaddd315ec9",
    "files": {
      "report.html": {
        "filename": "report.html",
        "type": "text/html",
        "language": "HTML",
        "raw_url": "https://gist.githubusercontent.com/vishalmsawant/1d1b5c2688c9726d5343bbaddd315ec9/raw/3f0c41c715ae8ce32d17b3cc6fa2e3f5d1e0065d/report.html",
        "size": 62436
      }
    },
    "public": true,
    "created_at": "2025-11-20T21:12:24Z",
    "updated_at": "2025-11-20T21:12:24Z",
    "description": "Automated HTML Report",
    "comments": 0,
    "user": null,
    "comments_enabled": true,
    "comments_url": "https://api.github.com/gists/1d1b5c2688c9726d5343bbaddd315ec9/comments",
    "owner": {
      "login": "vishalmsawant",
      "id": 191273169,
      "node_id": "U_kgDOC2aY0Q",
      "avatar_url": "https://avatars.githubusercontent.com/u/191273169?v=4",
      "gravatar_id": "",
      "url": "https://api.github.com/users/vishalmsawant",
      "html_url": "https://github.com/vishalmsawant",
      "followers_url": "https://api.github.com/users/vishalmsawant/followers",
      "following_url": "https://api.github.com/users/vishalmsawant/following{/other_user}",
      "gists_url": "https://api.github.com/users/vishalmsawant/gists{/gist_id}",
      "starred_url": "https://api.github.com/users/vishalmsawant/starred{/owner}{/repo}",
      "subscriptions_url": "https://api.github.com/users/vishalmsawant/subscriptions",
      "organizations_url": "https://api.github.com/users/vishalmsawant/orgs",
      "repos_url": "https://api.github.com/users/vishalmsawant/repos",
      "events_url": "https://api.github.com/users/vishalmsawant/events{/privacy}",
      "received_events_url": "https://api.github.com/users/vishalmsawant/received_events",
      "type": "User",
      "user_view_type": "public",
      "site_admin": false
    },
    "truncated": false
  },
  {
    "url": "https://api.github.com/gists/84ac90c472cc035edc09e3b15a5fe3c7",
    "forks_url": "https://api.github.com/gists/84ac90c472cc035edc09e3b15a5fe3c7/forks",
    "commits_url": "https://api.github.com/gists/84ac90c472cc035edc09e3b15a5fe3c7/commits",
    "id": "84ac90c472cc035edc09e3b15a5fe3c7",
    "node_id": "G_kwDOAF-wA9oAIDg0YWM5MGM0NzJjYzAzNWVkYzA5ZTNiMTVhNWZlM2M3",
    "git_pull_url": "https://gist.github.com/84ac90c472cc035edc09e3b15a5fe3c7.git",
    "git_push_url": "https://gist.github.com/84ac90c472cc035edc09e3b15a5fe3c7.git",
    "html_url": "https://gist.github.com/choco-bot/84ac90c472cc035edc09e3b15a5fe3c7",
    "files": {
      "FilesSnapshot.xml": {
        "filename": "FilesSnapshot.xml",
        "type": "application/xml",
        "language": "XML",
        "raw_url": "https://gist.githubusercontent.com/choco-bot/84ac90c472cc035edc09e3b15a5fe3c7/raw/18792c86fc24fde6443aa2c18f9bb72c9fa7dd28/FilesSnapshot.xml",
        "size": 604
      },
      "Install.txt": {
        "filename": "Install.txt",
        "type": "text/plain",
        "language": "Text",
        "raw_url": "https://gist.githubusercontent.com/choco-bot/84ac90c472cc035edc09e3b15a5fe3c7/raw/c8ec139fa678663eb88dcdab7a6a7f304bb01255/Install.txt",
        "size": 48542
      },
      "_Summary.md": {
        "filename": "_Summary.md",
        "type": "text/markdown",
        "language": "Markdown",
        "raw_url": "https://gist.githubusercontent.com/choco-bot/84ac90c472cc035edc09e3b15a5fe3c7/raw/ccd7fa23ddb15e29c3969524ded96aa53f6b47ac/_Summary.md",
        "size": 701
      }
    },
    "public": true,
    "created_at": "2025-11-20T21:11:28Z",
    "updated_at": "2025-11-20T21:11:28Z",
    "description": "netscan.portable v6.2.1 - Failed - Package Tests Results",
    "comments": 0,
    "user": null,
    "comments_enabled": true,
    "comments_url": "https://api.github.com/gists/84ac90c472cc035edc09e3b15a5fe3c7/comments",
    "owner": {
      "login": "choco-bot",
      "id": 6270979,
      "node_id": "MDQ6VXNlcjYyNzA5Nzk=",
      "avatar_url": "https://avatars.githubusercontent.com/u/6270979?v=4",
      "gravatar_id": "",
      "url": "https://api.github.com/users/choco-bot",
      "html_url": "https://github.com/choco-bot",
      "followers_url": "https://api.github.com/users/choco-bot/followers",
      "following_url": "https://api.github.com/users/choco-bot/following{/other_user}",
      "gists_url": "https://api.github.com/users/choco-bot/gists{/gist_id}",
      "starred_url": "https://api.github.com/users/choco-bot/starred{/owner}{/repo}",
      "subscriptions_url": "https://api.github.com/users/choco-bot/subscriptions",
      "organizations_url": "https://api.github.com/users/choco-bot/orgs",
      "repos_url": "https://api.github.com/users/choco-bot/repos",
      "events_url": "https://api.github.com/users/choco-bot/events{/privacy}",
      "received_events_url": "https://api.github.com/users/choco-bot/received_events",
      "type": "User",
      "user_view_type": "public",
      "site_admin": false
    },
    "truncated": false
  },
  {
    "url": "https://api.github.com/gists/f12a87de435f80e2307d5cec1cbfe69b",
    "forks_url": "https://api.github.com/gists/f12a87de435f80e2307d5cec1cbfe69b/forks",
    "commits_url": "https://api.github.com/gists/f12a87de435f80e2307d5cec1cbfe69b/commits",
    "id": "f12a87de435f80e2307d5cec1cbfe69b",
    "node_id": "G_kwDODCd0utoAIGYxMmE4N2RlNDM1ZjgwZTIzMDdkNWNlYzFjYmZlNjli",
    "git_pull_url": "https://gist.github.com/f12a87de435f80e2307d5cec1cbfe69b.git",
    "git_push_url": "https://gist.github.com/f12a87de435f80e2307d5cec1cbfe69b.git",
    "html_url": "https://gist.github.com/amaweb-unifesp/f12a87de435f80e2307d5cec1cbfe69b",
    "files": {
      "teclado-4.html": {
        "filename": "teclado-4.html",
        "type": "text/html",
        "language": "HTML",
        "raw_url": "https://gist.githubusercontent.com/amaweb-unifesp/f12a87de435f80e2307d5cec1cbfe69b/raw/5d6242d808613a49bf372e2a1a4e2fa11ff779aa/teclado-4.html",
        "size": 11396
      }
    },
    "public": true,
    "created_at": "2025-11-20T21:11:19Z",
    "updated_at": "2025-11-20T21:14:05Z",
    "description": "teclado-4",
    "comments": 0,
    "user": null,
    "comments_enabled": true,
    "comments_url": "https://api.github.com/gists/f12a87de435f80e2307d5cec1cbfe69b/comments",
    "owner": {
      "login": "amaweb-unifesp",
      "id": 203912378,
      "node_id": "U_kgDODCd0ug",
      "avatar_url": "https://avatars.githubusercontent.com/u/203912378?v=4",
      "gravatar_id": "",
      "url": "https://api.github.com/users/amaweb-unifesp",
      "html_url": "https://github.com/amaweb-unifesp",
      "followers_url": "https://api.github.com/users/amaweb-unifesp/followers",
      "following_url": "https://api.github.com/users/amaweb-unifesp/following{/other_user}",
      "gists_url": "https://api.github.com/users/amaweb-unifesp/gists{/gist_id}",
      "starred_url": "https://api.github.com/users/amaweb-unifesp/starred{/owner}{/repo}",
      "subscriptions_url": "https://api.github.com/users/amaweb-unifesp/subscriptions",
      "organizations_url": "https://api.github.com/users/amaweb-unifesp/orgs",
      "repos_url": "https://api.github.com/users/amaweb-unifesp/repos",
      "events_url": "https://api.github.com/users/amaweb-unifesp/events{/privacy}",
      "received_events_url": "https://api.github.com/users/amaweb-unifesp/received_events",
      "type": "User",
      "user_view_type": "public",
      "site_admin": false
    },
    "truncated": false
  },
  {
    "url": "https://api.github.com/gists/1a932a7d0fec344fba419d58bd4f3adc",
    "forks_url": "https://api.github.com/gists/1a932a7d0fec344fba419d58bd4f3adc/forks",
    "commits_url": "https://api.github.com/gists/1a932a7d0fec344fba419d58bd4f3adc/commits",
    "id": "1a932a7d0fec344fba419d58bd4f3adc",
    "node_id": "G_kwDOC2aY0doAIDFhOTMyYTdkMGZlYzM0NGZiYTQxOWQ1OGJkNGYzYWRj",
    "git_pull_url": "https://gist.github.com/1a932a7d0fec344fba419d58bd4f3adc.git",
    "git_push_url": "https://gist.github.com/1a932a7d0fec344fba419d58bd4f3adc.git",
    "html_url": "https://gist.github.com/vishalmsawant/1a932a7d0fec344fba419d58bd4f3adc",
    "files": {
      "report.html": {
        "filename": "report.html",
        "type": "text/html",
        "language": "HTML",
        "raw_url": "https://gist.githubusercontent.com/vishalmsawant/1a932a7d0fec344fba419d58bd4f3adc/raw/3f0c41c715ae8ce32d17b3cc6fa2e3f5d1e0065d/report.html",
        "size": 62436
      }
    },
    "public": true,
    "created_at": "2025-11-20T21:10:52Z",
    "updated_at": "2025-11-20T21:10:52Z",
    "description": "Automated HTML Report",
    "comments": 0,
    "user": null,
    "comments_enabled": true,
    "comments_url": "https://api.github.com/gists/1a932a7d0fec344fba419d58bd4f3adc/comments",
    "owner": {
      "login": "vishalmsawant",
      "id": 191273169,
      "node_id": "U_kgDOC2aY0Q",
      "avatar_url": "https://avatars.githubusercontent.com/u/191273169?v=4",
      "gravatar_id": "",
      "url": "https://api.github.com/users/vishalmsawant",
      "html_url": "https://github.com/vishalmsawant",
      "followers_url": "https://api.github.com/users/vishalmsawant/followers",
      "following_url": "https://api.github.com/users/vishalmsawant/following{/other_user}",
      "gists_url": "https://api.github.com/users/vishalmsawant/gists{/gist_id}",
      "starred_url": "https://api.github.com/users/vishalmsawant/starred{/owner}{/repo}",
      "subscriptions_url": "https://api.github.com/users/vishalmsawant/subscriptions",
      "organizations_url": "https://api.github.com/users/vishalmsawant/orgs",
      "repos_url": "https://api.github.com/users/vishalmsawant/repos",
      "events_url": "https://api.github.com/users/vishalmsawant/events{/privacy}",
      "received_events_url": "https://api.github.com/users/vishalmsawant/received_events",
      "type": "User",
      "user_view_type": "public",
      "site_admin": false
    },
    "truncated": false
  },
  {
    "url": "https://api.github.com/gists/63f6edd05fec039feae6c8c615db52e2",
    "forks_url": "https://api.github.com/gists/63f6edd05fec039feae6c8c615db52e2/forks",
    "commits_url": "https://api.github.com/gists/63f6edd05fec039feae6c8c615db52e2/commits",
    "id": "63f6edd05fec039feae6c8c615db52e2",
    "node_id": "G_kwDOAA_Di9oAIDYzZjZlZGQwNWZlYzAzOWZlYWU2YzhjNjE1ZGI1MmUy",
    "git_pull_url": "https://gist.github.com/63f6edd05fec039feae6c8c615db52e2.git",
    "git_push_url": "https://gist.github.com/63f6edd05fec039feae6c8c615db52e2.git",
    "html_url": "https://gist.github.com/ShelbyZ/63f6edd05fec039feae6c8c615db52e2",
    "files": {
      "fluent-bit.conf": {
        "filename": "fluent-bit.conf",
        "type": "text/plain",
        "language": null,
        "raw_url": "https://gist.githubusercontent.com/ShelbyZ/63f6edd05fec039feae6c8c615db52e2/raw/34f7115514acaf2ecb8d26923a1edb26f95603fb/fluent-bit.conf",
        "size": 11063
      },
      "fluent-bit.log": {
        "filename": "fluent-bit.log",
        "type": "text/plain",
        "language": null,
        "raw_url": "https://gist.githubusercontent.com/ShelbyZ/63f6edd05fec039feae6c8c615db52e2/raw/c60d24ccfc254bf1ad0b78415994943d874ce29e/fluent-bit.log",
        "size": 2583569
      },
      "valgrind.log": {
        "filename": "valgrind.log",
        "type": "text/plain",
        "language": null,
        "raw_url": "https://gist.githubusercontent.com/ShelbyZ/63f6edd05fec039feae6c8c615db52e2/raw/43782e66b936b55c3ea82f511ee6857acc13f992/valgrind.log",
        "size": 58807
      }
    },
    "public": true,
    "created_at": "2025-11-20T21:09:56Z",
    "updated_at": "2025-11-20T21:14:39Z",
    "description": "fix: properly handle IPv6 addresses in HTTP Host headers- https://github.com/fluent/fluent-bit/pull/11181",
    "comments": 0,
    "user": null,
    "comments_enabled": true,
    "comments_url": "https://api.github.com/gists/63f6edd05fec039feae6c8c615db52e2/comments",
    "owner": {
      "login": "ShelbyZ",
      "id": 1033099,
      "node_id": "MDQ6VXNlcjEwMzMwOTk=",
      "avatar_url": "https://avatars.githubusercontent.com/u/1033099?v=4",
      "gravatar_id": "",
      "url": "https://api.github.com/users/ShelbyZ",
      "html_url": "https://github.com/ShelbyZ",
      "followers_url": "https://api.github.com/users/ShelbyZ/followers",
      "following_url": "https://api.github.com/users/ShelbyZ/following{/other_user}",
      "gists_url": "https://api.github.com/users/ShelbyZ/gists{/gist_id}",
      "starred_url": "https://api.github.com/users/ShelbyZ/starred{/owner}{/repo}",
      "subscriptions_url": "https://api.github.com/users/ShelbyZ/subscriptions",
      "organizations_url": "https://api.github.com/users/ShelbyZ/orgs",
      "repos_url": "https://api.github.com/users/ShelbyZ/repos",
      "events_url": "https://api.github.com/users/ShelbyZ/events{/privacy}",
      "received_events_url": "https://api.github.com/users/ShelbyZ/received_events",
      "type": "User",
      "user_view_type": "public",
      "site_admin": false
    },
    "truncated": false
  },
  {
    "url": "https://api.github.com/gists/3dbecd6ed96a0a2759881b75c4121bb1",
    "forks_url": "https://api.github.com/gists/3dbecd6ed96a0a2759881b75c4121bb1/forks",
    "commits_url": "https://api.github.com/gists/3dbecd6ed96a0a2759881b75c4121bb1/commits",
    "id": "3dbecd6ed96a0a2759881b75c4121bb1",
    "node_id": "G_kwDOAF-wA9oAIDNkYmVjZDZlZDk2YTBhMjc1OTg4MWI3NWM0MTIxYmIx",
    "git_pull_url": "https://gist.github.com/3dbecd6ed96a0a2759881b75c4121bb1.git",
    "git_push_url": "https://gist.github.com/3dbecd6ed96a0a2759881b75c4121bb1.git",
    "html_url": "https://gist.github.com/choco-bot/3dbecd6ed96a0a2759881b75c4121bb1",
    "files": {
      "FilesSnapshot.xml": {
        "filename": "FilesSnapshot.xml",
        "type": "application/xml",
        "language": "XML",
        "raw_url": "https://gist.githubusercontent.com/choco-bot/3dbecd6ed96a0a2759881b75c4121bb1/raw/3a497c1bc3f8da209c055f84b5cf380e370aaeb0/FilesSnapshot.xml",
        "size": 1245
      },
      "Install.txt": {
        "filename": "Install.txt",
        "type": "text/plain",
        "language": "Text",
        "raw_url": "https://gist.githubusercontent.com/choco-bot/3dbecd6ed96a0a2759881b75c4121bb1/raw/8ff18f4cc47ebe179dd44316b962aafc3a99d72a/Install.txt",
        "size": 405544
      },
      "Uninstall.txt": {
        "filename": "Uninstall.txt",
        "type": "text/plain",
        "language": "Text",
        "raw_url": "https://gist.githubusercontent.com/choco-bot/3dbecd6ed96a0a2759881b75c4121bb1/raw/c777f902d4188a2b0e490dd7287edefc44174848/Uninstall.txt",
        "size": 55280
      },
      "_Summary.md": {
        "filename": "_Summary.md",
        "type": "text/markdown",
        "language": "Markdown",
        "raw_url": "https://gist.githubusercontent.com/choco-bot/3dbecd6ed96a0a2759881b75c4121bb1/raw/dd5df4cb98deef23d4836b56a3b5e533883ad4e8/_Summary.md",
        "size": 505
      }
    },
    "public": true,
    "created_at": "2025-11-20T21:09:31Z",
    "updated_at": "2025-11-20T21:09:32Z",
    "description": "dolphin-dev v2509.476.0-dev - Passed - Package Tests Results",
    "comments": 0,
    "user": null,
    "comments_enabled": true,
    "comments_url": "https://api.github.com/gists/3dbecd6ed96a0a2759881b75c4121bb1/comments",
    "owner": {
      "login": "choco-bot",
      "id": 6270979,
      "node_id": "MDQ6VXNlcjYyNzA5Nzk=",
      "avatar_url": "https://avatars.githubusercontent.com/u/6270979?v=4",
      "gravatar_id": "",
      "url": "https://api.github.com/users/choco-bot",
      "html_url": "https://github.com/choco-bot",
      "followers_url": "https://api.github.com/users/choco-bot/followers",
      "following_url": "https://api.github.com/users/choco-bot/following{/other_user}",
      "gists_url": "https://api.github.com/users/choco-bot/gists{/gist_id}",
      "starred_url": "https://api.github.com/users/choco-bot/starred{/owner}{/repo}",
      "subscriptions_url": "https://api.github.com/users/choco-bot/subscriptions",
      "organizations_url": "https://api.github.com/users/choco-bot/orgs",
      "repos_url": "https://api.github.com/users/choco-bot/repos",
      "events_url": "https://api.github.com/users/choco-bot/events{/privacy}",
      "received_events_url": "https://api.github.com/users/choco-bot/received_events",
      "type": "User",
      "user_view_type": "public",
      "site_admin": false
    },
    "truncated": false
  },
  {
    "url": "https://api.github.com/gists/a04b086998dfae7ce6f310d55db662a0",
    "forks_url": "https://api.github.com/gists/a04b086998dfae7ce6f310d55db662a0/forks",
    "commits_url": "https://api.github.com/gists/a04b086998dfae7ce6f310d55db662a0/commits",
    "id": "a04b086998dfae7ce6f310d55db662a0",
    "node_id": "G_kwDODpeIddoAIGEwNGIwODY5OThkZmFlN2NlNmYzMTBkNTVkYjY2MmEw",
    "git_pull_url": "https://gist.github.com/a04b086998dfae7ce6f310d55db662a0.git",
    "git_push_url": "https://gist.github.com/a04b086998dfae7ce6f310d55db662a0.git",
    "html_url": "https://gist.github.com/technycio/a04b086998dfae7ce6f310d55db662a0",
    "files": {
      "blockchain.ts": {
        "filename": "blockchain.ts",
        "type": "video/MP2T",
        "language": "TypeScript",
        "raw_url": "https://gist.githubusercontent.com/technycio/a04b086998dfae7ce6f310d55db662a0/raw/30f77226ad7d0ae012c1e15ae373999667453f25/blockchain.ts",
        "size": 4002
      }
    },
    "public": true,
    "created_at": "2025-11-20T21:09:13Z",
    "updated_at": "2025-11-20T21:09:13Z",
    "description": "A simulated Crypto Blockchain",
    "comments": 0,
    "user": null,
    "comments_enabled": true,
    "comments_url": "https://api.github.com/gists/a04b086998dfae7ce6f310d55db662a0/comments",
    "owner": {
      "login": "technycio",
      "id": 244811893,
      "node_id": "U_kgDODpeIdQ",
      "avatar_url": "https://avatars.githubusercontent.com/u/244811893?v=4",
      "gravatar_id": "",
      "url": "https://api.github.com/users/technycio",
      "html_url": "https://github.com/technycio",
      "followers_url": "https://api.github.com/users/technycio/followers",
      "following_url": "https://api.github.com/users/technycio/following{/other_user}",
      "gists_url": "https://api.github.com/users/technycio/gists{/gist_id}",
      "starred_url": "https://api.github.com/users/technycio/starred{/owner}{/repo}",
      "subscriptions_url": "https://api.github.com/users/technycio/subscriptions",
      "organizations_url": "https://api.github.com/users/technycio/orgs",
      "repos_url": "https://api.github.com/users/technycio/repos",
      "events_url": "https://api.github.com/users/technycio/events{/privacy}",
      "received_events_url": "https://api.github.com/users/technycio/received_events",
      "type": "User",
      "user_view_type": "public",
      "site_admin": false
    },
    "truncated": false
  },
  {
    "url": "https://api.github.com/gists/e2fd958340b4a64bc1616fa20f8e138d",
    "forks_url": "https://api.github.com/gists/e2fd958340b4a64bc1616fa20f8e138d/forks",
    "commits_url": "https://api.github.com/gists/e2fd958340b4a64bc1616fa20f8e138d/commits",
    "id": "e2fd958340b4a64bc1616fa20f8e138d",
    "node_id": "G_kwDOAYLrTdoAIGUyZmQ5NTgzNDBiNGE2NGJjMTYxNmZhMjBmOGUxMzhk",
    "git_pull_url": "https://gist.github.com/e2fd958340b4a64bc1616fa20f8e138d.git",
    "git_push_url": "https://gist.github.com/e2fd958340b4a64bc1616fa20f8e138d.git",
    "html_url": "https://gist.github.com/MichaelAndoni/e2fd958340b4a64bc1616fa20f8e138d",
    "files": {
      "gistfile1.txt": {
        "filename": "gistfile1.txt",
        "type": "text/plain",
        "language": "Text",
        "raw_url": "https://gist.githubusercontent.com/MichaelAndoni/e2fd958340b4a64bc1616fa20f8e138d/raw/0d35582dc59a86d25c255b1a3b7b1ca2a80cf185/gistfile1.txt",
        "size": 242
      }
    },
    "public": true,
    "created_at": "2025-11-20T21:08:47Z",
    "updated_at": "2025-11-20T21:08:47Z",
    "description": "Privacy Policy",
    "comments": 0,
    "user": null,
    "comments_enabled": true,
    "comments_url": "https://api.github.com/gists/e2fd958340b4a64bc1616fa20f8e138d/comments",
    "owner": {
      "login": "MichaelAndoni",
      "id": 25357133,
      "node_id": "MDQ6VXNlcjI1MzU3MTMz",
      "avatar_url": "https://avatars.githubusercontent.com/u/25357133?v=4",
      "gravatar_id": "",
      "url": "https://api.github.com/users/MichaelAndoni",
      "html_url": "https://github.com/MichaelAndoni",
      "followers_url": "https://api.github.com/users/MichaelAndoni/followers",
      "following_url": "https://api.github.com/users/MichaelAndoni/following{/other_user}",
      "gists_url": "https://api.github.com/users/MichaelAndoni/gists{/gist_id}",
      "starred_url": "https://api.github.com/users/MichaelAndoni/starred{/owner}{/repo}",
      "subscriptions_url": "https://api.github.com/users/MichaelAndoni/subscriptions",
      "organizations_url": "https://api.github.com/users/MichaelAndoni/orgs",
      "repos_url": "https://api.github.com/users/MichaelAndoni/repos",
      "events_url": "https://api.github.com/users/MichaelAndoni/events{/privacy}",
      "received_events_url": "https://api.github.com/users/MichaelAndoni/received_events",
      "type": "User",
      "user_view_type": "public",
      "site_admin": false
    },
    "truncated": false
  },
  {
    "url": "https://api.github.com/gists/6c122fdbe4039621f93711978e09f1fa",
    "forks_url": "https://api.github.com/gists/6c122fdbe4039621f93711978e09f1fa/forks",
    "commits_url": "https://api.github.com/gists/6c122fdbe4039621f93711978e09f1fa/commits",
    "id": "6c122fdbe4039621f93711978e09f1fa",
    "node_id": "G_kwDOAmXo89oAIDZjMTIyZmRiZTQwMzk2MjFmOTM3MTE5NzhlMDlmMWZh",
    "git_pull_url": "https://gist.github.com/6c122fdbe4039621f93711978e09f1fa.git",
    "git_push_url": "https://gist.github.com/6c122fdbe4039621f93711978e09f1fa.git",
    "html_url": "https://gist.github.com/danielrosehill/6c122fdbe4039621f93711978e09f1fa",
    "files": {
      "parquet-file-association-tad.md": {
        "filename": "parquet-file-association-tad.md",
        "type": "text/markdown",
        "language": "Markdown",
        "raw_url": "https://gist.githubusercontent.com/danielrosehill/6c122fdbe4039621f93711978e09f1fa/raw/6dc1f95a51b3bc362410f525fbadf9036daefd80/parquet-file-association-tad.md",
        "size": 3793
      }
    },
    "public": true,
    "created_at": "2025-11-20T21:08:19Z",
    "updated_at": "2025-11-20T21:08:19Z",
    "description": "How to Create a File Association for .parquet Files with Tad on Linux",
    "comments": 0,
    "user": null,
    "comments_enabled": true,
    "comments_url": "https://api.github.com/gists/6c122fdbe4039621f93711978e09f1fa/comments",
    "owner": {
      "login": "danielrosehill",
      "id": 40233203,
      "node_id": "MDQ6VXNlcjQwMjMzMjAz",
      "avatar_url": "https://avatars.githubusercontent.com/u/40233203?v=4",
      "gravatar_id": "",
      "url": "https://api.github.com/users/danielrosehill",
      "html_url": "https://github.com/danielrosehill",
      "followers_url": "https://api.github.com/users/danielrosehill/followers",
      "following_url": "https://api.github.com/users/danielrosehill/following{/other_user}",
      "gists_url": "https://api.github.com/users/danielrosehill/gists{/gist_id}",
      "starred_url": "https://api.github.com/users/danielrosehill/starred{/owner}{/repo}",
      "subscriptions_url": "https://api.github.com/users/danielrosehill/subscriptions",
      "organizations_url": "https://api.github.com/users/danielrosehill/orgs",
      "repos_url": "https://api.github.com/users/danielrosehill/repos",
      "events_url": "https://api.github.com/users/danielrosehill/events{/privacy}",
      "received_events_url": "https://api.github.com/users/danielrosehill/received_events",
      "type": "User",
      "user_view_type": "public",
      "site_admin": false
    },
    "truncated": false
  },
  {
    "url": "https://api.github.com/gists/01780943ffe71aca850fedbbb36704f9",
    "forks_url": "https://api.github.com/gists/01780943ffe71aca850fedbbb36704f9/forks",
    "commits_url": "https://api.github.com/gists/01780943ffe71aca850fedbbb36704f9/commits",
    "id": "01780943ffe71aca850fedbbb36704f9",
    "node_id": "G_kwDOBqLDEdoAIDAxNzgwOTQzZmZlNzFhY2E4NTBmZWRiYmIzNjcwNGY5",
    "git_pull_url": "https://gist.github.com/01780943ffe71aca850fedbbb36704f9.git",
    "git_push_url": "https://gist.github.com/01780943ffe71aca850fedbbb36704f9.git",
    "html_url": "https://gist.github.com/mattsebastianh/01780943ffe71aca850fedbbb36704f9",
    "files": {
      "classroom_organizer.py": {
        "filename": "classroom_organizer.py",
        "type": "application/x-python",
        "language": "Python",
        "raw_url": "https://gist.githubusercontent.com/mattsebastianh/01780943ffe71aca850fedbbb36704f9/raw/67d1223c3b138e4604b63bc971b921dae3651dd3/classroom_organizer.py",
        "size": 1097
      },
      "classroom_organizer_adv.py": {
        "filename": "classroom_organizer_adv.py",
        "type": "application/x-python",
        "language": "Python",
        "raw_url": "https://gist.githubusercontent.com/mattsebastianh/01780943ffe71aca850fedbbb36704f9/raw/0bf21cd1f5a216bf6fa6496239f320b51d9525f4/classroom_organizer_adv.py",
        "size": 1554
      },
      "instructions.md": {
        "filename": "instructions.md",
        "type": "text/markdown",
        "language": "Markdown",
        "raw_url": "https://gist.githubusercontent.com/mattsebastianh/01780943ffe71aca850fedbbb36704f9/raw/528cacbd2c20078deae7a1d9193e1f8afe11d41a/instructions.md",
        "size": 331
      },
      "roster.py": {
        "filename": "roster.py",
        "type": "application/x-python",
        "language": "Python",
        "raw_url": "https://gist.githubusercontent.com/mattsebastianh/01780943ffe71aca850fedbbb36704f9/raw/4e873f24f2d59092926bfa1d68bd35c7165f09b6/roster.py",
        "size": 1311
      },
      "script.py": {
        "filename": "script.py",
        "type": "application/x-python",
        "language": "Python",
        "raw_url": "https://gist.githubusercontent.com/mattsebastianh/01780943ffe71aca850fedbbb36704f9/raw/f84d4e19d078716d4ec34b15c4127a6d32ce3695/script.py",
        "size": 1282
      },
      "script2.py": {
        "filename": "script2.py",
        "type": "application/x-python",
        "language": "Python",
        "raw_url": "https://gist.githubusercontent.com/mattsebastianh/01780943ffe71aca850fedbbb36704f9/raw/b1ab035cb203f6d961bcf6acf9aaa527d7465288/script2.py",
        "size": 461
      }
    },
    "public": true,
    "created_at": "2025-11-20T21:08:14Z",
    "updated_at": "2025-11-20T21:08:14Z",
    "description": "New Teacher in Town: Mastering Iterables and Iterators",
    "comments": 0,
    "user": null,
    "comments_enabled": true,
    "comments_url": "https://api.github.com/gists/01780943ffe71aca850fedbbb36704f9/comments",
    "owner": {
      "login": "mattsebastianh",
      "id": 111330065,
      "node_id": "U_kgDOBqLDEQ",
      "avatar_url": "https://avatars.githubusercontent.com/u/111330065?v=4",
      "gravatar_id": "",
      "url": "https://api.github.com/users/mattsebastianh",
      "html_url": "https://github.com/mattsebastianh",
      "followers_url": "https://api.github.com/users/mattsebastianh/followers",
      "following_url": "https://api.github.com/users/mattsebastianh/following{/other_user}",
      "gists_url": "https://api.github.com/users/mattsebastianh/gists{/gist_id}",
      "starred_url": "https://api.github.com/users/mattsebastianh/starred{/owner}{/repo}",
      "subscriptions_url": "https://api.github.com/users/mattsebastianh/subscriptions",
      "organizations_url": "https://api.github.com/users/mattsebastianh/orgs",
      "repos_url": "https://api.github.com/users/mattsebastianh/repos",
      "events_url": "https://api.github.com/users/mattsebastianh/events{/privacy}",
      "received_events_url": "https://api.github.com/users/mattsebastianh/received_events",
      "type": "User",
      "user_view_type": "public",
      "site_admin": false
    },
    "truncated": false
  },
  {
    "url": "https://api.github.com/gists/a75c98ed0b9c1271ef67310cd944b10b",
    "forks_url": "https://api.github.com/gists/a75c98ed0b9c1271ef67310cd944b10b/forks",
    "commits_url": "https://api.github.com/gists/a75c98ed0b9c1271ef67310cd944b10b/commits",
    "id": "a75c98ed0b9c1271ef67310cd944b10b",
    "node_id": "G_kwDODnRev9oAIGE3NWM5OGVkMGI5YzEyNzFlZjY3MzEwY2Q5NDRiMTBi",
    "git_pull_url": "https://gist.github.com/a75c98ed0b9c1271ef67310cd944b10b.git",
    "git_push_url": "https://gist.github.com/a75c98ed0b9c1271ef67310cd944b10b.git",
    "html_url": "https://gist.github.com/MalShlip/a75c98ed0b9c1271ef67310cd944b10b",
    "files": {
      "zbackdoor.c": {
        "filename": "zbackdoor.c",
        "type": "text/plain",
        "language": "C",
        "raw_url": "https://gist.githubusercontent.com/MalShlip/a75c98ed0b9c1271ef67310cd944b10b/raw/eebe723fbb50b42567425aa867b7af081fdec217/zbackdoor.c",
        "size": 5484
      }
    },
    "public": true,
    "created_at": "2025-11-20T21:07:32Z",
    "updated_at": "2025-11-20T21:07:32Z",
    "description": "",
    "comments": 0,
    "user": null,
    "comments_enabled": true,
    "comments_url": "https://api.github.com/gists/a75c98ed0b9c1271ef67310cd944b10b/comments",
    "owner": {
      "login": "MalShlip",
      "id": 242507455,
      "node_id": "U_kgDODnRevw",
      "avatar_url": "https://avatars.githubusercontent.com/u/242507455?v=4",
      "gravatar_id": "",
      "url": "https://api.github.com/users/MalShlip",
      "html_url": "https://github.com/MalShlip",
      "followers_url": "https://api.github.com/users/MalShlip/followers",
      "following_url": "https://api.github.com/users/MalShlip/following{/other_user}",
      "gists_url": "https://api.github.com/users/MalShlip/gists{/gist_id}",
      "starred_url": "https://api.github.com/users/MalShlip/starred{/owner}{/repo}",
      "subscriptions_url": "https://api.github.com/users/MalShlip/subscriptions",
      "organizations_url": "https://api.github.com/users/MalShlip/orgs",
      "repos_url": "https://api.github.com/users/MalShlip/repos",
      "events_url": "https://api.github.com/users/MalShlip/events{/privacy}",
      "received_events_url": "https://api.github.com/users/MalShlip/received_events",
      "type": "User",
      "user_view_type": "public",
      "site_admin": false
    },
    "truncated": false
  },
  {
    "url": "https://api.github.com/gists/f6accda5946989d842efbeebb34c25b7",
    "forks_url": "https://api.github.com/gists/f6accda5946989d842efbeebb34c25b7/forks",
    "commits_url": "https://api.github.com/gists/f6accda5946989d842efbeebb34c25b7/commits",
    "id": "f6accda5946989d842efbeebb34c25b7",
    "node_id": "G_kwDOC2aY0doAIGY2YWNjZGE1OTQ2OTg5ZDg0MmVmYmVlYmIzNGMyNWI3",
    "git_pull_url": "https://gist.github.com/f6accda5946989d842efbeebb34c25b7.git",
    "git_push_url": "https://gist.github.com/f6accda5946989d842efbeebb34c25b7.git",
    "html_url": "https://gist.github.com/vishalmsawant/f6accda5946989d842efbeebb34c25b7",
    "files": {
      "report.html": {
        "filename": "report.html",
        "type": "text/html",
        "language": "HTML",
        "raw_url": "https://gist.githubusercontent.com/vishalmsawant/f6accda5946989d842efbeebb34c25b7/raw/fa2a3fc09b9519e40efaf41e5066cb36a0b4d44a/report.html",
        "size": 62430
      }
    },
    "public": true,
    "created_at": "2025-11-20T21:07:11Z",
    "updated_at": "2025-11-20T21:07:12Z",
    "description": "Automated HTML Report",
    "comments": 0,
    "user": null,
    "comments_enabled": true,
    "comments_url": "https://api.github.com/gists/f6accda5946989d842efbeebb34c25b7/comments",
    "owner": {
      "login": "vishalmsawant",
      "id": 191273169,
      "node_id": "U_kgDOC2aY0Q",
      "avatar_url": "https://avatars.githubusercontent.com/u/191273169?v=4",
      "gravatar_id": "",
      "url": "https://api.github.com/users/vishalmsawant",
      "html_url": "https://github.com/vishalmsawant",
      "followers_url": "https://api.github.com/users/vishalmsawant/followers",
      "following_url": "https://api.github.com/users/vishalmsawant/following{/other_user}",
      "gists_url": "https://api.github.com/users/vishalmsawant/gists{/gist_id}",
      "starred_url": "https://api.github.com/users/vishalmsawant/starred{/owner}{/repo}",
      "subscriptions_url": "https://api.github.com/users/vishalmsawant/subscriptions",
      "organizations_url": "https://api.github.com/users/vishalmsawant/orgs",
      "repos_url": "https://api.github.com/users/vishalmsawant/repos",
      "events_url": "https://api.github.com/users/vishalmsawant/events{/privacy}",
      "received_events_url": "https://api.github.com/users/vishalmsawant/received_events",
      "type": "User",
      "user_view_type": "public",
      "site_admin": false
    },
    "truncated": false
  }
]