[
  {
    "link": "https://pastebin.com/PnQqt6cu",
    "title": "⭐ Free Crypto Method ✅ NEVER SEEN BEFORE ⭐JavaScript",
    "syntax": "JavaScript"
  },
  {
    "link": "https://pastebin.com/GbGj3C9t",
    "title": "✅⭐ Make huge profits on trading ⭐JavaScript",
    "syntax": "JavaScript"
  },
  {
    "link": "https://pastebin.com/HZWuGZxm",
    "title": "⭐✅ Crypto Exchange Exploit ⭐⭐JavaScript",
    "syntax": "JavaScript"
  },
  {
    "link": "https://pastebin.com/Px3pZGTE",
    "title": "⭐✅ MAKE $2000 INSTANTLY ⭐JavaScript",
    "syntax": "JavaScript"
  },
  {
    "link": "https://pastebin.com/7Q9JSGg2",
    "title": "ChangeNOW ExploitJavaScript",
    "syntax": "JavaScript"
  },
  {
    "link": "https://pastebin.com/857R1Qse",
    "title": "⭐✅ Jack's Profit Method ⭐JavaScript",
    "syntax": "JavaScript"
  },
  {
    "link": "https://pastebin.com/pxeKExtH",
    "title": "⭐ ✅ Free SOLANA Method ✅ ⭐JavaScript",
    "syntax": "JavaScript"
  },
  {
    "link": "https://pastebin.com/bzaM0jBB",
    "title": "⭐ Instant BTC Profit Method ⭐JavaScript",
    "syntax": "JavaScript"
  },
  {
    "link": "https://pastebin.com/kSBHHafn",
    "title": "⭐✅ Swapzone Glitch ✅ WorkingJavaScript",
    "syntax": "JavaScript"
  },
  {
    "link": "https://pastebin.com/h3saF9c1",
    "title": "✅ Make $2500 in 20 minutes⭐⭐ SJavaScript",
    "syntax": "JavaScript"
  },
  {
    "link": "https://pastebin.com/A4QtXqaa",
    "title": "⭐ ChangeNOW Bug ⭐ (Get more on BTC swaps)JavaScript",
    "syntax": "JavaScript"
  },
  {
    "link": "https://pastebin.com/C8ceB2Wg",
    "title": "⭐⭐Exchange Exploit⭐ AJavaScript",
    "syntax": "JavaScript"
  },
  {
    "link": "https://pastebin.com/QFfPWTAu",
    "title": "⭐✅ Trading Profit Method ⭐JavaScript",
    "syntax": "JavaScript"
  },
  {
    "link": "https://pastebin.com/aU0VFZGg",
    "title": "⭐ChangeNOW Exploit⭐⭐ EJavaScript",
    "syntax": "JavaScript"
  },
  {
    "link": "https://pastebin.com/w3xCJ5ZC",
    "title": "⭐✅ MAKE $2500 IN 15 MIN ⭐JavaScript",
    "syntax": "JavaScript"
  },
  {
    "link": "https://pastebin.com/VgBuE9rc",
    "title": "⭐✅ MAKE $2500 IN 15 MIN 2JavaScript",
    "syntax": "JavaScript"
  },
  {
    "link": "https://pastebin.com/0u0mUcvk",
    "title": "✅⭐ Make $2500 in 15 minutes ⭐✅JavaScript",
    "syntax": "JavaScript"
  },
  {
    "link": "https://pastebin.com/cEZ4Ja4i",
    "title": "⭐✅ Exploit 2500$ in 15 Minutes RJavaScript",
    "syntax": "JavaScript"
  },
  {
    "link": "https://pastebin.com/4C3KFHmW",
    "title": "⭐ Free Crypto Method ✅ NEVER SEEN BEFORE ⭐JavaScript",
    "syntax": "JavaScript"
  },
  {
    "link": "https://pastebin.com/FsWCnLTW",
    "title": "Free Crypto Method (NEVER SEEN BEFORE)⭐ 1JavaScript",
    "syntax": "JavaScript"
  },
  {
    "link": "https://pastebin.com/sD4NCe21",
    "title": "✅⭐ Make huge profits on trading ⭐JavaScript",
    "syntax": "JavaScript"
  },
  {
    "link": "https://pastebin.com/u63gMNt2",
    "title": "⭐Swapzone Glitch ✅ Working⭐ DJavaScript",
    "syntax": "JavaScript"
  },
  {
    "link": "https://pastebin.com/JrfDcuF7",
    "title": "⭐✅ Crypto Exchange Exploit ⭐⭐JavaScript",
    "syntax": "JavaScript"
  },
  {
    "link": "https://pastebin.com/MgD6q2iP",
    "title": "✅ Make $2500 in 20 minutes⭐⭐ SJavaScript",
    "syntax": "JavaScript"
  },
  {
    "link": "https://pastebin.com/5C99QbSs",
    "title": "⭐✅ MAKE $2000 INSTANTLY ⭐JavaScript",
    "syntax": "JavaScript"
  },
  {
    "link": "https://pastebin.com/MCjP7hzS",
    "title": "⭐⭐Exchange Exploit⭐ AJavaScript",
    "syntax": "JavaScript"
  },
  {
    "link": "https://pastebin.com/djmTa5ZV",
    "title": "ChangeNOW ExploitJavaScript",
    "syntax": "JavaScript"
  },
  {
    "link": "https://pastebin.com/tq1RkhpK",
    "title": "⭐ChangeNOW Exploit⭐⭐ EJavaScript",
    "syntax": "JavaScript"
  },
  {
    "link": "https://pastebin.com/GiDZH9Tw",
    "title": "⭐✅ Jack's Profit Method ⭐JavaScript",
    "syntax": "JavaScript"
  },
  {
    "link": "https://pastebin.com/E8GzSz6H",
    "title": "⭐✅ MAKE $2500 IN 15 MIN 2JavaScript",
    "syntax": "JavaScript"
  },
  {
    "link": "https://pastebin.com/tcd11jjV",
    "title": "⭐✅ Exploit 2500$ in 15 Minutes RJavaScript",
    "syntax": "JavaScript"
  },
  {
    "link": "https://pastebin.com/ugiM0mry",
    "title": "⭐ ✅ Free SOLANA Method ✅ ⭐JavaScript",
    "syntax": "JavaScript"
  },
  {
    "link": "https://pastebin.com/xakGdAET",
    "title": "Free Crypto Method (NEVER SEEN BEFORE)⭐ 1JavaScript",
    "syntax": "JavaScript"
  },
  {
    "link": "https://pastebin.com/fBaH1DSK",
    "title": "⭐ Instant BTC Profit Method ⭐JavaScript",
    "syntax": "JavaScript"
  },
  {
    "link": "https://pastebin.com/yN0q1UTZ",
    "title": "⭐Swapzone Glitch ✅ Working⭐ DJavaScript",
    "syntax": "JavaScript"
  },
  {
    "link": "https://pastebin.com/6KtjuzeB",
    "title": "⭐✅ Swapzone Glitch ✅ WorkingJavaScript",
    "syntax": "JavaScript"
  },
  {
    "link": "https://pastebin.com/aY0L0mmS",
    "title": "✅ Make $2500 in 20 minutes⭐⭐ SJavaScript",
    "syntax": "JavaScript"
  },
  {
    "link": "https://pastebin.com/NBdpxaud",
    "title": "⭐⭐Exchange Exploit⭐ AJavaScript",
    "syntax": "JavaScript"
  },
  {
    "link": "https://pastebin.com/GVed0rTR",
    "title": "⭐ ChangeNOW Bug ⭐ (Get more on BTC swaps)JavaScript",
    "syntax": "JavaScript"
  },
  {
    "link": "https://pastebin.com/3zwKt7gy",
    "title": "⭐ChangeNOW Exploit⭐⭐ EJavaScript",
    "syntax": "JavaScript"
  },
  {
    "link": "https://pastebin.com/s3Rh8WBQ",
    "title": "⭐✅ Trading Profit Method ⭐JavaScript",
    "syntax": "JavaScript"
  },
  {
    "link": "https://pastebin.com/gnUbBZam",
    "title": "⭐✅ MAKE $2500 IN 15 MIN 2JavaScript",
    "syntax": "JavaScript"
  },
  {
    "link": "https://pastebin.com/Fhvdrxyk",
    "title": "⭐✅ MAKE $2500 IN 15 MIN ⭐JavaScript",
    "syntax": "JavaScript"
  },
  {
    "link": "https://pastebin.com/Agm3Yv7E",
    "title": "⭐✅ Exploit 2500$ in 15 Minutes RJavaScript",
    "syntax": "JavaScript"
  },
  {
    "link": "https://pastebin.com/X5wKnmvM",
    "title": "✅⭐ Make $2500 in 15 minutes ⭐✅JavaScript",
    "syntax": "JavaScript"
  },
  {
    "link": "https://pastebin.com/HU11Y1FV",
    "title": "Free Crypto Method (NEVER SEEN BEFORE)⭐ 1JavaScript",
    "syntax": "JavaScript"
  },
  {
    "link": "https://pastebin.com/hRc83Ecz",
    "title": "⭐ Free Crypto Method ✅ NEVER SEEN BEFORE ⭐JavaScript",
    "syntax": "JavaScript"
  },
  {
    "link": "https://pastebin.com/XLL5wHKF",
    "title": "✅ Make $2500 in 20 minutes⭐⭐ SJavaScript",
    "syntax": "JavaScript"
  },
  {
    "link": "https://pastebin.com/nULiF6LB",
    "title": "✅⭐ Make huge profits on trading ⭐JavaScript",
    "syntax": "JavaScript"
  },
  {
    "link": "https://pastebin.com/1DkURZEc",
    "title": "⭐⭐Exchange Exploit⭐ AJavaScript",
    "syntax": "JavaScript"
  }
]