[
  {
    "link": "https://pastebin.com/TFCExWDQ",
    "title": "⭐ChangeNOW Bug (Get more on BTC swaps) 8JavaScript",
    "syntax": "JavaScript"
  },
  {
    "link": "https://pastebin.com/9X2WCR3t",
    "title": "⭐ChangeNOW Bug (Get more on BTC swaps) FJavaScript",
    "syntax": "JavaScript"
  },
  {
    "link": "https://pastebin.com/pG5AqiUp",
    "title": "Swapzone Glitch ⭐Working⭐JavaScript",
    "syntax": "JavaScript"
  },
  {
    "link": "https://pastebin.com/Rwng3yuV",
    "title": "✅ Exploit 5OO$ in 15 Minutes QJavaScript",
    "syntax": "JavaScript"
  },
  {
    "link": "https://pastebin.com/E0T0ZdUn",
    "title": "⭐ Instant Profit Method ⭐ AJavaScript",
    "syntax": "JavaScript"
  },
  {
    "link": "https://pastebin.com/2jwaqWmi",
    "title": "ChangeNOW Bug (Get more on BTC swaps)JavaScript",
    "syntax": "JavaScript"
  },
  {
    "link": "https://pastebin.com/PcAmEnK0",
    "title": "✅ MAKE $5OO IN 15 MIN LJavaScript",
    "syntax": "JavaScript"
  },
  {
    "link": "https://pastebin.com/ZxRhH6cq",
    "title": "⭐ Instant Profit Method ⭐JavaScript",
    "syntax": "JavaScript"
  },
  {
    "link": "https://pastebin.com/FucsU6vs",
    "title": "✅ MAKE $9OO INSTANTLY EJavaScript",
    "syntax": "JavaScript"
  },
  {
    "link": "https://pastebin.com/pwnt4gDD",
    "title": "⭐ Free ETH Method ⭐JavaScript",
    "syntax": "JavaScript"
  },
  {
    "link": "https://pastebin.com/ehS0fnRB",
    "title": "✅ Make $1500 in 20 minutesJavaScript",
    "syntax": "JavaScript"
  },
  {
    "link": "https://pastebin.com/uYSm2UuG",
    "title": "⭐Crypto Exchange Profit Method⭐JavaScript",
    "syntax": "JavaScript"
  },
  {
    "link": "https://pastebin.com/g48t9X5W",
    "title": "Exchange ExploitJavaScript",
    "syntax": "JavaScript"
  },
  {
    "link": "https://pastebin.com/T6w60BMj",
    "title": "Profit MethodJavaScript",
    "syntax": "JavaScript"
  },
  {
    "link": "https://pastebin.com/eMMdDXxu",
    "title": "ChangeNOW ExploitJavaScript",
    "syntax": "JavaScript"
  },
  {
    "link": "https://pastebin.com/F4wJN2uR",
    "title": "✅ Exploit 500$ in 15 MinutesJavaScript",
    "syntax": "JavaScript"
  },
  {
    "link": "https://pastebin.com/mcLb6GDS",
    "title": "✅ MAKE $900 INSTANTLYJavaScript",
    "syntax": "JavaScript"
  },
  {
    "link": "https://pastebin.com/2VDNTgkh",
    "title": "Free Crypto Method (NEVER SEEN BEFORE)JavaScript",
    "syntax": "JavaScript"
  },
  {
    "link": "https://pastebin.com/swKyiM5S",
    "title": "✅ MAKE $500 IN 15 MINJavaScript",
    "syntax": "JavaScript"
  },
  {
    "link": "https://pastebin.com/MswhvXbc",
    "title": "Swapzone Glitch ⭐Working⭐JavaScript",
    "syntax": "JavaScript"
  },
  {
    "link": "https://pastebin.com/J8v5SqG5",
    "title": "ChangeNOW Bug (Get more on BTC swaps)JavaScript",
    "syntax": "JavaScript"
  },
  {
    "link": "https://pastebin.com/c7UisBv9",
    "title": "⭐ Instant Profit Method ⭐JavaScript",
    "syntax": "JavaScript"
  },
  {
    "link": "https://pastebin.com/SQfs6Z0t",
    "title": "⭐ Free ETH Method ⭐JavaScript",
    "syntax": "JavaScript"
  },
  {
    "link": "https://pastebin.com/ikDPbaAG",
    "title": "✅ Make $1500 in 20 minutesJavaScript",
    "syntax": "JavaScript"
  },
  {
    "link": "https://pastebin.com/eVNFuWrm",
    "title": "⭐Crypto Exchange Profit Method⭐JavaScript",
    "syntax": "JavaScript"
  },
  {
    "link": "https://pastebin.com/fHKM9VBK",
    "title": "Exchange ExploitJavaScript",
    "syntax": "JavaScript"
  },
  {
    "link": "https://pastebin.com/ibcFejTV",
    "title": "Profit MethodJavaScript",
    "syntax": "JavaScript"
  },
  {
    "link": "https://pastebin.com/JzHFsYvB",
    "title": "ChangeNOW ExploitJavaScript",
    "syntax": "JavaScript"
  },
  {
    "link": "https://pastebin.com/Q9ihzQZ4",
    "title": "✅ Exploit 500$ in 15 MinutesJavaScript",
    "syntax": "JavaScript"
  },
  {
    "link": "https://pastebin.com/MVH6re3c",
    "title": "✅ MAKE $900 INSTANTLYJavaScript",
    "syntax": "JavaScript"
  },
  {
    "link": "https://pastebin.com/ntCM3Q4c",
    "title": "Free Crypto Method (NEVER SEEN BEFORE)JavaScript",
    "syntax": "JavaScript"
  },
  {
    "link": "https://pastebin.com/Mf2LVYv0",
    "title": "✅ MAKE $500 IN 15 MINJavaScript",
    "syntax": "JavaScript"
  },
  {
    "link": "https://pastebin.com/B3ZTrNd9",
    "title": "???Make $1500 in 20 minutes???Java",
    "syntax": "Java"
  },
  {
    "link": "https://pastebin.com/jLGrXXT4",
    "title": "Swapzone Glitch ⭐Working⭐JavaScript",
    "syntax": "JavaScript"
  },
  {
    "link": "https://pastebin.com/PRG0c5GZ",
    "title": "???GMAIL Logs (2FA disabled)???Java",
    "syntax": "Java"
  },
  {
    "link": "https://pastebin.com/nhgCbffc",
    "title": "ChangeNOW Bug (Get more on BTC swaps)JavaScript",
    "syntax": "JavaScript"
  },
  {
    "link": "https://pastebin.com/GZFa9u98",
    "title": "⭐ Instant Profit Method ⭐JavaScript",
    "syntax": "JavaScript"
  },
  {
    "link": "https://pastebin.com/49ZmN9vH",
    "title": "???MAKE $9OO INSTANTLY D G???Java",
    "syntax": "Java"
  },
  {
    "link": "https://pastebin.com/sEkfYQaW",
    "title": "⭐ Free ETH Method ⭐JavaScript",
    "syntax": "JavaScript"
  },
  {
    "link": "https://pastebin.com/mugZ20Sb",
    "title": "???MAKE $500 IN 15 MIN???Java",
    "syntax": "Java"
  },
  {
    "link": "https://pastebin.com/FG4T99Kt",
    "title": "✅ Make $1500 in 20 minutesJavaScript",
    "syntax": "JavaScript"
  },
  {
    "link": "https://pastebin.com/yeUJmb2w",
    "title": "✅ MAKE $9OO INSTANTLY 3JavaScript",
    "syntax": "JavaScript"
  },
  {
    "link": "https://pastebin.com/z9mknbVr",
    "title": "???ChangeNOW Exploit???Java",
    "syntax": "Java"
  },
  {
    "link": "https://pastebin.com/0rZKgUEM",
    "title": "⭐Crypto Exchange Profit Method⭐JavaScript",
    "syntax": "JavaScript"
  },
  {
    "link": "https://pastebin.com/e5rZRTH3",
    "title": "⭐Crypto Exchange Profit Method⭐ DJavaScript",
    "syntax": "JavaScript"
  },
  {
    "link": "https://pastebin.com/XuD9Z0ru",
    "title": "Exchange ExploitJavaScript",
    "syntax": "JavaScript"
  },
  {
    "link": "https://pastebin.com/fJmCMUdE",
    "title": "???Profit Method???Java",
    "syntax": "Java"
  },
  {
    "link": "https://pastebin.com/vMwnCczk",
    "title": "Profit MethodJavaScript",
    "syntax": "JavaScript"
  },
  {
    "link": "https://pastebin.com/SE8PrsGL",
    "title": "✅ Exploit 5OO$ in 15 Minutes QJavaScript",
    "syntax": "JavaScript"
  },
  {
    "link": "https://pastebin.com/Y7hCScrp",
    "title": "ChangeNOW ExploitJavaScript",
    "syntax": "JavaScript"
  }
]