[
  {
    "link": "https://pastebin.com/MPtQd50u?source=archive",
    "title": "Nightlight - vs Fearlings",
    "syntax": ""
  },
  {
    "link": "https://pastebin.com/se8vFWyz?source=archive",
    "title": "Fearlings - Incorporeal",
    "syntax": ""
  },
  {
    "link": "https://pastebin.com/HvE1GVNx?source=archive",
    "title": "Katherine - Languages",
    "syntax": ""
  },
  {
    "link": "https://pastebin.com/Pq9rYYyZ?source=archive",
    "title": "Ombric - Paint",
    "syntax": ""
  },
  {
    "link": "https://pastebin.com/KqZnw7ie?source=archive",
    "title": "Ombric - SC Defenses",
    "syntax": ""
  },
  {
    "link": "https://pastebin.com/1NqSgdqf?source=archive",
    "title": "Ombric - Hedge",
    "syntax": ""
  },
  {
    "link": "https://pastebin.com/ZV6ReeJu?source=archive",
    "title": "Ombric - Santoff Clausen",
    "syntax": ""
  },
  {
    "link": "https://pastebin.com/xhM95yev?source=archive",
    "title": "Ombric - Big if true",
    "syntax": ""
  },
  {
    "link": "https://pastebin.com/SaaJyGFt?source=archive",
    "title": "Ombric - Languages",
    "syntax": ""
  },
  {
    "link": "https://pastebin.com/kdGkbe8b?source=archive",
    "title": "MiM - Moonbeams cont.",
    "syntax": ""
  },
  {
    "link": "https://pastebin.com/vYCpDMFh?source=archive",
    "title": "Moonbeam - Dispels Fearlings",
    "syntax": ""
  },
  {
    "link": "https://pastebin.com/9TewtA1G?source=archive",
    "title": "Pitch - Sense + Cloak",
    "syntax": ""
  },
  {
    "link": "https://pastebin.com/aKhy3wXV?source=archive",
    "title": "Nightlight - Leaving the cave",
    "syntax": ""
  },
  {
    "link": "https://pastebin.com/LvwGqVPx?source=archive",
    "title": "MiM - Moonbeams",
    "syntax": ""
  }
]